Workbook
Name ClientData: Client!$1:$152
Name ClientID: Link!$O$3
Name Codes: Link!$C$8:$D$112
Name DedCode: Link!$J$3
Name DedEmp: Link!$J$2
Name DedName: Link!$J$4
Name DeductionCodes: Link!$I$8:$K$50
Name DeductionData: Deductions!$A$1:$K$1638
Name DedValue: Link!$J$5
Name EmpID: Link!$D$2
Name EmpName: Link!$D$3
Name IgnoreCodes: Link!$F$8:$G$39
Name MinDiff: Link!$D$4
Name SBCcodes: Link!$M$8:$P$65
Name SBCdata: SBC!$A$1:$S$1000
Name SBCID: Link!$O$2
Name SBCType: Link!$O$4
Name SysCode: Link!$G$3
Name SysEmpID: Link!$G$2
Name SysItemName: Link!$G$4
Name SystemData: System!$A$1:$L$3000
Name SysValue: Link!$G$5

Sheet הערות
A1: בס"ד
A4: 1 | B4: בגליון DEDUCTIONS יש רכיבים 13 ו- 16 שאין להם ביטוי בנתוני הלקוח
A5: 2 | B5: בגליון DEDUCTIONS יש רכיב 9 שמתייחס להחזרי הוצאות. בנתוני הלקוח זה רק תמורה ממכירת אופציות. צריך להבין מה עושים עם שאר החזרי ההוצאות
A6: 3 | B6: בגלל שמסכמים את כל הרכיבים שיש להם אותו מספר רכיב, אז בגליון הממצאים, אין התייחסות לשםפ הרכיב בנתוני הלקוח - כיון שיש מספר רכיבים עם אותו קוד

Sheet Client
A1: No. | B1: ID | C1: Z-ID | D1: Employee's name | E1: Department - Cost Centre | F1: Employee Class | G1: Employment Status | H1: Start date | I1: End date | J1: New Annual salaries | K1: Payroll Comments | L1: Salary | M1: Global overtime | N1: Total - Monthly | O1: ESPP Contribution % | P1: ESPP Contribution - Amount | Q1: ESPP Catchups for December 2024 | R1: CEO Bonus | S1: Travel Allowance | T1: Commissions | U1: Phone value | V1: BIK- Birthday Gift (to be grossed up) | W1: Referral Bonus | X1: Salary Arrears- Aug'25 & Sept'25 | Y1: Israel First Year Bonus Scheme: | Z1: Retention Bonus | AA1: Corporate Bonus | AB1: BIK Health Insurance (to be grossed up) | AC1: BIK - Mobile Reimbursment - to be grossed up | AD1: BIK - Meals - October 2025 (EE bears the tax) | AE1: BIK Lunch Meals- (to be grossed up) October 2025 | AF1: BIK Dinner Meals- (to be grossed up) October 2025 | AG1: BIK -Holiday Gifts- Sept 2025 (taxes borne by employer) | AH1: Wedding Gift (need to pay and gross up) | AI1: ESPP refunds | AJ1: Tution Reimbursement Benefit- Pay and Tax will borne by EE | AK1: Spot Bonus- EE bears the tax | AL1: Patent Bonus- EE bears the tax | AM1: Standard Days | AN1: Standard hours | AO1: Actual working days | AP1: Actual work hours | AQ1: Vacation days | AR1: Sick days | AS1: Reserve Duty | AT1: Advance Payment | AU1: Reimbursement | AV1: Comments
A2: 4 | B2: 306689712 | C2: Z22252 | D2: Leonid Geldin | E2: 2450 | F2: Fulltime Employee | G2: Active | H2: 43788 | J2: 630230.22 | L2: =J2/12*70% -> 36763.429 | M2: =J2/12*30% -> 15755.755 | N2: =SUM(L2:M2) -> 52519.185 | O2: 15 | P2: =(N2+W2+X2+AA2+T2+R2)*O2% -> 7877.8777 | S2: 315 | V2: 0 | AB2: 154 | AC2: 115 | AD2: 1000 | AM2: 21 | AN2: =AM2*8.4 -> 176.4 | AO2: =AM2-AQ2-AR2 -> 19.5 | AP2: =AO2*8.4 -> 163.8 | AQ2: 1.5 | AR2: 0 | AU2: 1580
A3: 6 | B3: 32655482 | C3: Z22251 | D3: Nadav Pozmantir | E3: 2410 | F3: Fulltime Employee | G3: Active | H3: 43905 | J3: 625007 | L3: =J3/12*70% -> 36458.742 | M3: =J3/12*30% -> 15625.175 | N3: =SUM(L3:M3) -> 52083.917 | O3: 15 | P3: =(N3+W3+X3+AA3+T3+R3)*O3% -> 7812.5875 | S3: 315 | V3: 0 | AB3: 154 | AC3: 115 | AD3: 1000 | AM3: 21 | AN3: =AM3*8.4 -> 176.4 | AO3: =AM3-AQ3-AR3 -> 8 | AP3: =AO3*8.4 -> 67.2 | AQ3: 3 | AR3: 10
A4: 8 | B4: 65965949 | C4: Z22256 | D4: Ido Katz | E4: 2410 | F4: Fulltime Employee | G4: Active | H4: 44005 | J4: 612002.66 | L4: =J4/12*70% -> 35700.155 | M4: =J4/12*30% -> 15300.067 | N4: =SUM(L4:M4) -> 51000.222 | O4: 15 | P4: =(N4+W4+X4+AA4+T4+R4)*O4% -> 7650.0333 | S4: 315 | V4: 0 | AB4: 154 | AC4: 115 | AD4: 1000 | AM4: 21 | AN4: =AM4*8.4 -> 176.4 | AO4: =AM4-AQ4-AR4 -> 19 | AP4: =AO4*8.4 -> 159.6 | AQ4: 0 | AR4: 2 | AU4: 1860
A5: 11 | B5: 35699578 | C5: Z22254 | D5: Elad Kolberg | E5: 2885 | F5: Fulltime Employee | G5: Active | H5: 44087 | J5: 735201.69 | L5: =J5/12*70% -> 42886.765 | M5: =J5/12*30% -> 18380.042 | N5: =SUM(L5:M5) -> 61266.807 | O5: 10 | P5: =(N5+W5+X5+AA5+T5+R5)*O5% -> 6126.6807 | S5: 315 | V5: 0 | AB5: 154 | AC5: 115 | AD5: 1000 | AM5: 21 | AN5: =AM5*8.4 -> 176.4 | AO5: =AM5-AQ5-AR5 -> 20 | AP5: =AO5*8.4 -> 168 | AQ5: 0 | AR5: 1
A6: 12 | B6: 39997325 | C6: Z22255 | D6: Ariel Nemtzov | E6: 2410 | F6: Fulltime Employee | G6: Active | H6: 44087 | J6: 555531 | L6: =J6/12*70% -> 32405.975 | M6: =J6/12*30% -> 13888.275 | N6: =SUM(L6:M6) -> 46294.25 | O6: 15 | P6: =(N6+W6+X6+AA6+T6+R6)*O6% -> 6944.1375 | S6: 315 | V6: 0 | AB6: 154 | AC6: 115 | AD6: 1000 | AM6: 21 | AN6: =AM6*8.4 -> 176.4 | AO6: =AM6-AQ6-AR6 -> 20 | AP6: =AO6*8.4 -> 168 | AQ6: 0 | AR6: 1 | AU6: 391
A7: 14 | B7: 38075941 | C7: Z22260 | D7: Danny Sabag | E7: 2410 | F7: Fulltime Employee | G7: Active | H7: 44122 | J7: 546551 | L7: =J7/12*70% -> 31882.142 | M7: =J7/12*30% -> 13663.775 | N7: =SUM(L7:M7) -> 45545.917 | O7: 8 | P7: =(N7+W7+X7+AA7+T7+R7)*O7% -> 3643.6733 | S7: 315 | V7: 0 | AB7: 154 | AC7: 115 | AD7: 999.96 | AM7: 21 | AN7: =AM7*8.4 -> 176.4 | AO7: =AM7-AQ7-AR7 -> 21 | AP7: =AO7*8.4 -> 176.4 | AQ7: 0 | AR7: 0 | AU7: 208
A8: 15 | B8: 66713272 | C8: Z22259 | D8: Oz Molaim | E8: 2410 | F8: Fulltime Employee | G8: Active | H8: 44130 | J8: 530201 | L8: =J8/12*70% -> 30928.392 | M8: =J8/12*30% -> 13255.025 | N8: =SUM(L8:M8) -> 44183.417 | O8: 15 | P8: =(N8+W8+X8+AA8+T8+R8)*O8% -> 6627.5125 | S8: 315 | V8: 0 | AB8: 154 | AC8: 115 | AD8: 940.5 | AM8: 21 | AN8: =AM8*8.4 -> 176.4 | AO8: =AM8-AQ8-AR8 -> 20 | AP8: =AO8*8.4 -> 168 | AQ8: 0 | AR8: 1
A9: 16 | B9: 306939349 | C9: Z22261 | D9: Maya Zax | E9: 2180 | F9: Parttime Employee 60% working position | G9: Active | H9: 44164 | J9: 256261.37 | K9: Parttime Employee 60% working position | L9: =J9/12*70% -> 14948.58 | M9: =J9/12*30% -> 6406.5342 | N9: =SUM(L9:M9) -> 21355.114 | O9: 0 | P9: =(N9+W9+X9+AA9+T9+R9)*O9% -> 0 | S9: 315 | V9: 0 | AB9: 154 | AC9: 115 | AD9: 700 | AM9: 21 | AN9: =AM9*8.4 -> 176.4 | AO9: =AM9-AQ9-AR9 -> 21 | AP9: =AO9*8.4 -> 176.4 | AQ9: 0 | AR9: 0
A10: 17 | B10: 300123221 | C10: Z22405 | D10: Adi Adrai | E10: 2410 | F10: Fulltime Employee | G10: Active | H10: 44350 | J10: 610388 | L10: =J10/12*70% -> 35605.967 | M10: =J10/12*30% -> 15259.7 | N10: =SUM(L10:M10) -> 50865.667 | O10: 15 | P10: =(N10+W10+X10+AA10+T10+R10)*O10% -> 7629.85 | S10: 315 | V10: 0 | AB10: 154 | AC10: 115 | AD10: 738 | AM10: 21 | AN10: =AM10*8.4 -> 176.4 | AO10: =AM10-AQ10-AR10 -> 11 | AP10: =AO10*8.4 -> 92.4 | AQ10: 10 | AR10: 0
A11: 21 | B11: 332407659 | C11: Z22756 | D11: Esther Shteinberg | E11: 2180 | F11: Fulltime Employee | G11: Active | H11: 44395 | J11: 486311 | L11: =J11/12*70% -> 28368.142 | M11: =J11/12*30% -> 12157.775 | N11: =SUM(L11:M11) -> 40525.917 | O11: 15 | P11: =(N11+W11+X11+AA11+T11+R11)*O11% -> 6078.8875 | S11: 315 | V11: 0 | AB11: 154 | AC11: 115 | AD11: 1000 | AM11: 21 | AN11: =AM11*8.4 -> 176.4 | AO11: =AM11-AQ11-AR11 -> 8 | AP11: =AO11*8.4 -> 67.2 | AQ11: 0 | AR11: 13
A12: 22 | B12: 201570793 | C12: Z22704 | D12: Adam Hudeda | E12: 2450 | F12: Fulltime Employee | G12: Active | H12: 44395 | J12: 505167 | L12: =J12/12*70% -> 29468.075 | M12: =J12/12*30% -> 12629.175 | N12: =SUM(L12:M12) -> 42097.25 | O12: 15 | P12: =(N12+W12+X12+AA12+T12+R12)*O12% -> 6314.5875 | S12: 315 | V12: 0 | AB12: 154 | AC12: 115 | AD12: 1000 | AM12: 21 | AN12: =AM12*8.4 -> 176.4 | AO12: =AM12-AQ12-AR12 -> 20 | AP12: =AO12*8.4 -> 168 | AQ12: 1 | AR12: 0 | AU12: 70
A13: 23 | B13: 27385756 | C13: Z22874 | D13: Ofer Yarom | E13: 2540 | F13: Fulltime Employee | G13: Active | H13: 44424 | J13: 779032.26 | L13: =J13/12*70% -> 45443.548 | M13: =J13/12*30% -> 19475.806 | N13: =SUM(L13:M13) -> 64919.355 | O13: 15 | P13: =(N13+W13+X13+AA13+T13+R13)*O13% -> 9737.9032 | S13: 315 | V13: 0 | AB13: 154 | AC13: 115 | AD13: 995.72 | AM13: 21 | AN13: =AM13*8.4 -> 176.4 | AO13: =AM13-AQ13-AR13 -> 21 | AP13: =AO13*8.4 -> 176.4 | AQ13: 0 | AR13: 0
A14: 24 | B14: 316377191 | C14: Z23095 | D14: Lilach Wimisiner | E14: 2410 | F14: Fulltime Employee | G14: Active | H14: 44437 | J14: 509230 | L14: =J14/12*70% -> 29705.083 | M14: =J14/12*30% -> 12730.75 | N14: =SUM(L14:M14) -> 42435.833 | O14: 15 | P14: =(N14+W14+X14+AA14+T14+R14)*O14% -> 6365.375 | S14: 315 | V14: 0 | AB14: 154 | AC14: 115 | AD14: 967.96 | AM14: 21 | AN14: =AM14*8.4 -> 176.4 | AO14: =AM14-AQ14-AR14 -> 21 | AP14: =AO14*8.4 -> 176.4 | AQ14: 0 | AR14: 0
A15: 26 | B15: 206350936 | C15: Z23096 | D15: Dani Rubin | E15: 2885 | F15: Fulltime Employee | G15: Active | H15: 44441 | J15: 530530 | L15: =J15/12*70% -> 30947.583 | M15: =J15/12*30% -> 13263.25 | N15: =SUM(L15:M15) -> 44210.833 | O15: 15 | P15: =(N15+W15+X15+AA15+T15+R15)*O15% -> 6631.625 | S15: 315 | V15: 0 | AB15: 154 | AC15: 115 | AD15: 1000 | AM15: 21 | AN15: =AM15*8.4 -> 176.4 | AO15: =AM15-AQ15-AR15 -> 16 | AP15: =AO15*8.4 -> 134.4 | AQ15: 5 | AR15: 0
A16: 27 | B16: 207763806 | C16: Z23077 | D16: Jonathan Assayag | E16: 2885 | F16: Fulltime Employee | G16: Active | H16: 44451 | J16: 499180 | L16: =J16/12*70% -> 29118.833 | M16: =J16/12*30% -> 12479.5 | N16: =SUM(L16:M16) -> 41598.333 | O16: 15 | P16: =(N16+W16+X16+AA16+T16+R16)*O16% -> 6239.75 | S16: 315 | V16: 0 | AB16: 154 | AC16: 115 | AD16: 1000 | AM16: 21 | AN16: =AM16*8.4 -> 176.4 | AO16: =AM16-AQ16-AR16 -> 21 | AP16: =AO16*8.4 -> 176.4 | AQ16: 0 | AR16: 0
A17: 30 | B17: 21598768 | C17: Z23336 | D17: Gal Shvinkelstein | E17: 2410 | F17: Fulltime Employee | G17: Active | H17: 44473 | J17: 488298.8 | L17: =J17/12*70% -> 28484.097 | M17: =J17/12*30% -> 12207.47 | N17: =SUM(L17:M17) -> 40691.567 | O17: 1 | P17: =(N17+W17+X17+AA17+T17+R17)*O17% -> 406.91567 | S17: 315 | V17: 0 | AB17: 154 | AC17: 115 | AD17: 1000 | AM17: 21 | AN17: =AM17*8.4 -> 176.4 | AO17: =AM17-AQ17-AR17 -> 19 | AP17: =AO17*8.4 -> 159.6 | AQ17: 2 | AR17: 0 | AU17: 40
A18: 32 | B18: 307604256 | C18: Z23259 | D18: Gal Sosin | E18: 2410 | F18: Fulltime Employee | G18: Active | H18: 44486 | J18: 637738.5 | L18: =J18/12*70% -> 37201.412 | M18: =J18/12*30% -> 15943.462 | N18: =SUM(L18:M18) -> 53144.875 | O18: 0 | P18: =(N18+W18+X18+AA18+T18+R18)*O18% -> 0 | S18: 315 | V18: 150 | AB18: 154 | AC18: 115 | AD18: 1000 | AM18: 21 | AN18: =AM18*8.4 -> 176.4 | AO18: =AM18-AQ18-AR18 -> 20 | AP18: =AO18*8.4 -> 168 | AQ18: 0 | AR18: 1
A19: 35 | B19: 201270642 | C19: Z23824 | D19: Keren Zilberman | E19: 1580 | F19: Fulltime Employee | G19: Active | H19: 44516 | J19: 252167 | L19: =J19/12*70% -> 14709.742 | M19: =J19/12*30% -> 6304.175 | N19: =SUM(L19:M19) -> 21013.917 | O19: 7 | P19: =(N19+W19+X19+AA19+T19+R19)*O19% -> 1470.9742 | S19: 315 | V19: 0 | AB19: 154 | AC19: 115 | AD19: 1000 | AM19: 21 | AN19: =AM19*8.4 -> 176.4 | AO19: =AM19-AQ19-AR19 -> 20 | AP19: =AO19*8.4 -> 168 | AQ19: 0 | AR19: 1
A20: 38 | B20: 36983187 | C20: Z23746 | D20: Avner Eizner | E20: 2410 | F20: Fulltime Employee | G20: Active | H20: 44521 | J20: 561479 | L20: =J20/12*70% -> 32752.942 | M20: =J20/12*30% -> 14036.975 | N20: =SUM(L20:M20) -> 46789.917 | O20: 15 | P20: =(N20+W20+X20+AA20+T20+R20)*O20% -> 7018.4875 | S20: 315 | V20: 0 | AB20: 154 | AC20: 115 | AD20: 1000 | AM20: 21 | AN20: =AM20*8.4 -> 176.4 | AO20: =AM20-AQ20-AR20 -> 20 | AP20: =AO20*8.4 -> 168 | AQ20: 0 | AR20: 1
A21: 36 | B21: 207669821 | C21: Z24042 | D21: Amit Bar | E21: 2410 | F21: Fulltime Employee | G21: Active | H21: 44528 | J21: 330297 | L21: =J21/12*70% -> 19267.325 | M21: =J21/12*30% -> 8257.425 | N21: =SUM(L21:M21) -> 27524.75 | O21: 15 | P21: =(N21+W21+X21+AA21+T21+R21)*O21% -> 4128.7125 | S21: 315 | V21: 0 | AB21: 154 | AC21: 115 | AD21: 999.1 | AF21: 168.9 | AM21: 21 | AN21: =AM21*8.4 -> 176.4 | AO21: =AM21-AQ21-AR21 -> 7 | AP21: =AO21*8.4 -> 58.8 | AQ21: 14 | AR21: 0
A22: 41 | B22: 204287635 | C22: Z24237 | D22: Shoham Shimon Danino | E22: 2885 | F22: Fulltime Employee | G22: Active | H22: 44577 | J22: 594240 | L22: =J22/12*70% -> 34664 | M22: =J22/12*30% -> 14856 | N22: =SUM(L22:M22) -> 49520 | O22: 15 | P22: =(N22+W22+X22+AA22+T22+R22)*O22% -> 8666.1945 | S22: 315 | V22: 0 | W22: 8254.63 | AB22: 154 | AC22: 115 | AD22: 1000 | AM22: 21 | AN22: =AM22*8.4 -> 176.4 | AO22: =AM22-AQ22-AR22 -> 21 | AP22: =AO22*8.4 -> 176.4 | AQ22: 0 | AR22: 0
A23: 42 | B23: 204596795 | C23: Z24238 | D23: Roi Inbar | E23: 2885 | F23: Fulltime Employee | G23: Active | H23: 44577 | J23: 534600 | L23: =J23/12*70% -> 31185 | M23: =J23/12*30% -> 13365 | N23: =SUM(L23:M23) -> 44550 | O23: 15 | P23: =(N23+W23+X23+AA23+T23+R23)*O23% -> 6682.5 | S23: 315 | V23: 0 | AB23: 154 | AC23: 115 | AD23: 1000 | AM23: 21 | AN23: =AM23*8.4 -> 176.4 | AO23: =AM23-AQ23-AR23 -> 21 | AP23: =AO23*8.4 -> 176.4 | AQ23: 0 | AR23: 0
A24: 43 | B24: 302748843 | C24: Z24239 | D24: Samir Dabit | E24: 2410 | F24: Fulltime Employee | G24: Active | H24: 44581 | J24: 425930 | L24: =J24/12*70% -> 24845.917 | M24: =J24/12*30% -> 10648.25 | N24: =SUM(L24:M24) -> 35494.167 | O24: 0 | P24: =(N24+W24+X24+AA24+T24+R24)*O24% -> 0 | S24: 315 | V24: 0 | AB24: 154 | AC24: 115 | AD24: 1000 | AM24: 21 | AN24: =AM24*8.4 -> 176.4 | AO24: =AM24-AQ24-AR24 -> 21 | AP24: =AO24*8.4 -> 176.4 | AQ24: 0 | AR24: 0
A25: 45 | B25: 305357956 | C25: Z24467 | D25: Noam Yadar | E25: 2410 | F25: Fulltime Employee | G25: Active | H25: 44585 | J25: 489124.9 | L25: =J25/12*70% -> 28532.286 | M25: =J25/12*30% -> 12228.122 | N25: =M25+L25 -> 40760.408 | O25: 15 | P25: =(N25+W25+X25+AA25+T25+R25)*O25% -> 6114.0612 | S25: 315 | V25: 0 | AB25: 154 | AC25: 115 | AD25: 1000 | AM25: 21 | AN25: =AM25*8.4 -> 176.4 | AO25: =AM25-AQ25-AR25 -> 21 | AP25: =AO25*8.4 -> 176.4 | AQ25: 0 | AR25: 0
A26: 47 | B26: 318638038 | C26: Z24243 | D26: Eden Meyuhas | E26: 2885 | F26: Fulltime Employee | G26: Active | H26: 44620 | J26: 528900 | L26: =J26/12*70% -> 30852.5 | M26: =J26/12*30% -> 13222.5 | N26: =SUM(L26:M26) -> 44075 | O26: 15 | P26: =(N26+W26+X26+AA26+T26+R26)*O26% -> 6611.25 | S26: 315 | V26: 0 | AB26: 154 | AC26: 115 | AD26: 1000 | AM26: 21 | AN26: =AM26*8.4 -> 176.4 | AO26: =AM26-AQ26-AR26 -> 19 | AP26: =AO26*8.4 -> 159.6 | AQ26: 2 | AR26: 0 | AU26: 168
A27: 57 | B27: 40678740 | C27: Z25690 | D27: Ricky Levi | E27: 2250 | F27: Fulltime Employee | G27: Active | H27: 44713 | J27: 566000 | L27: =J27/12*70% -> 33016.667 | M27: =J27/12*30% -> 14150 | N27: =SUM(L27:M27) -> 47166.667 | O27: 15 | P27: =(N27+W27+X27+AA27+T27+R27)*O27% -> 7075 | S27: 315 | V27: 0 | AB27: 154 | AC27: 115 | AD27: 1000 | AM27: 21 | AN27: =AM27*8.4 -> 176.4 | AO27: =AM27-AQ27-AR27 -> 21 | AP27: =AO27*8.4 -> 176.4 | AQ27: 0 | AR27: 0 | AU27: 100
A28: 59 | B28: 66729690 | C28: Z25692 | D28: Elad Goren | E28: 2160 | F28: Fulltime Employee | G28: Active | H28: 44713 | J28: 726404 | L28: =J28/12*70% -> 42373.567 | M28: =J28/12*30% -> 18160.1 | N28: =SUM(L28:M28) -> 60533.667 | O28: 15 | P28: =(N28+W28+X28+AA28+T28+R28)*O28% -> 9080.05 | S28: 315 | V28: 150 | AB28: 154 | AC28: 115 | AD28: 1000 | AM28: 21 | AN28: =AM28*8.4 -> 176.4 | AO28: =AM28-AQ28-AR28 -> 21 | AP28: =AO28*8.4 -> 176.4 | AQ28: 0 | AR28: 0
A29: 60 | B29: 323235135 | C29: Z25693 | D29: Dmitry Kulik | E29: 2160 | F29: Fulltime Employee | G29: Active | H29: 44713 | J29: 699998 | L29: =J29/12*70% -> 40833.217 | M29: =J29/12*30% -> 17499.95 | N29: =SUM(L29:M29) -> 58333.167 | O29: 15 | P29: =(N29+W29+X29+AA29+T29+R29)*O29% -> 8749.975 | S29: 315 | V29: 0 | AB29: 154 | AC29: 115 | AD29: 986.52 | AM29: 21 | AN29: =AM29*8.4 -> 176.4 | AO29: =AM29-AQ29-AR29 -> 20 | AP29: =AO29*8.4 -> 168 | AQ29: 1 | AR29: 0
A30: 53 | B30: 304846652 | C30: Z25785 | D30: Dor Pizem | E30: 2410 | F30: Fulltime Employee | G30: Active | H30: 44720 | J30: 497998 | L30: =J30/12*70% -> 29049.883 | M30: =J30/12*30% -> 12449.95 | N30: =SUM(L30:M30) -> 41499.833 | O30: 10 | P30: =(N30+W30+X30+AA30+T30+R30)*O30% -> 4149.9833 | S30: 315 | V30: 0 | AB30: 154 | AC30: 115 | AD30: 999.71 | AM30: 21 | AN30: =AM30*8.4 -> 176.4 | AO30: =AM30-AQ30-AR30 -> 21 | AP30: =AO30*8.4 -> 176.4 | AQ30: 0 | AR30: 0 | AU30: 248
A31: 54 | B31: 321285512 | C31: Z25694 | D31: Vitaly Artemov | E31: 2160 | F31: Fulltime Employee | G31: Active | H31: 44721 | J31: 785030 | L31: =J31/12*70% -> 45793.417 | M31: =J31/12*30% -> 19625.75 | N31: =SUM(L31:M31) -> 65419.167 | O31: 8 | P31: =(N31+W31+X31+AA31+T31+R31)*O31% -> 5233.5333 | S31: 315 | V31: 0 | AB31: 154 | AC31: 115 | AD31: 1000 | AM31: 21 | AN31: =AM31*8.4 -> 176.4 | AO31: =AM31-AQ31-AR31 -> 21 | AP31: =AO31*8.4 -> 176.4 | AQ31: 0 | AR31: 0 | AU31: 70
A32: 55 | B32: 314349622 | C32: Z25730 | D32: Oleg Perah | E32: 2450 | F32: Fulltime Employee | G32: Active | H32: 44735 | J32: 519026 | L32: =J32/12*70% -> 30276.517 | M32: =J32/12*30% -> 12975.65 | N32: =SUM(L32:M32) -> 43252.167 | O32: 15 | P32: =(N32+W32+X32+AA32+T32+R32)*O32% -> 6487.825 | S32: 315 | V32: 0 | AB32: 154 | AC32: 115 | AD32: 1000 | AM32: 21 | AN32: =AM32*8.4 -> 176.4 | AO32: =AM32-AQ32-AR32 -> 21 | AP32: =AO32*8.4 -> 176.4 | AQ32: 0 | AR32: 0
A33: 56 | B33: 309341808 | C33: Z25802 | D33: Marat Khousid | E33: 2160 | F33: Fulltime Employee | G33: Active | H33: 44740 | J33: 791600 | L33: =J33/12*70% -> 46176.667 | M33: =J33/12*30% -> 19790 | N33: =SUM(L33:M33) -> 65966.667 | O33: 7 | P33: =(N33+W33+X33+AA33+T33+R33)*O33% -> 4617.6667 | S33: 315 | V33: 0 | AB33: 154 | AC33: 115 | AD33: 1000 | AM33: 21 | AN33: =AM33*8.4 -> 176.4 | AO33: =AM33-AQ33-AR33 -> 21 | AP33: =AO33*8.4 -> 176.4 | AQ33: 0 | AR33: 0
A34: 61 | B34: 13641527 | C34: Z25922 | D34: Gadi Goldbarg | E34: 2160 | F34: Fulltime Employee | G34: Active | H34: 44752 | J34: 587000 | L34: =J34/12*70% -> 34241.667 | M34: =J34/12*30% -> 14675 | N34: =SUM(L34:M34) -> 48916.667 | O34: 4 | P34: =(N34+W34+X34+AA34+T34+R34)*O34% -> 1956.6667 | S34: 315 | V34: 0 | AB34: 154 | AC34: 115 | AD34: 999.15 | AM34: 21 | AN34: =AM34*8.4 -> 176.4 | AO34: =AM34-AQ34-AR34 -> 21 | AP34: =AO34*8.4 -> 176.4 | AQ34: 0 | AR34: 0
A35: 62 | B35: 15931777 | C35: Z25938 | D35: Amir Tarkey | E35: 2160 | F35: Fulltime Employee | G35: Active | H35: 44759 | J35: 434000 | L35: =J35/12*70% -> 25316.667 | M35: =J35/12*30% -> 10850 | N35: =SUM(L35:M35) -> 36166.667 | O35: 15 | P35: =(N35+W35+X35+AA35+T35+R35)*O35% -> 5425 | S35: 315 | V35: 0 | AB35: 154 | AC35: 115 | AD35: 832.38 | AM35: 21 | AN35: =AM35*8.4 -> 176.4 | AO35: =AM35-AQ35-AR35 -> 21 | AP35: =AO35*8.4 -> 176.4 | AQ35: 0 | AR35: 0
A36: 65 | B36: 333801231 | C36: Z26198 | D36: Jon Joseba Gabilondo Angulo | E36: 2160 | F36: Fulltime Employee | G36: Active | H36: 44774 | J36: 726360 | L36: =J36/12*70% -> 42371 | M36: =J36/12*30% -> 18159 | N36: =SUM(L36:M36) -> 60530 | O36: 10 | P36: =(N36+W36+X36+AA36+T36+R36)*O36% -> 6053 | S36: 315 | V36: 0 | AB36: 154 | AC36: 115 | AD36: 999.5 | AM36: 21 | AN36: =AM36*8.4 -> 176.4 | AO36: =AM36-AQ36-AR36 -> 21 | AP36: =AO36*8.4 -> 176.4 | AQ36: 0 | AR36: 0
A37: 67 | B37: 32105199 | C37: Z26199 | D37: Eyal Lubelski | E37: 2160 | F37: Fulltime Employee | G37: Active | H37: 44774 | J37: 470000 | L37: =J37/12*70% -> 27416.667 | M37: =J37/12*30% -> 11750 | N37: =SUM(L37:M37) -> 39166.667 | O37: 8 | P37: =(N37+W37+X37+AA37+T37+R37)*O37% -> 3133.3333 | S37: 315 | V37: 0 | AB37: 154 | AC37: 115 | AD37: 965 | AM37: 21 | AN37: =AM37*8.4 -> 176.4 | AO37: =AM37-AQ37-AR37 -> 21 | AP37: =AO37*8.4 -> 176.4 | AQ37: 0 | AR37: 0
A38: 68 | B38: 34890491 | C38: Z26200 | D38: Bar Zukerman | E38: 2160 | F38: Fulltime Employee | G38: Active | H38: 44780 | J38: 634800 | L38: =J38/12*70% -> 37030 | M38: =J38/12*30% -> 15870 | N38: =SUM(L38:M38) -> 52900 | O38: 10 | P38: =(N38+W38+X38+AA38+T38+R38)*O38% -> 5290 | S38: 315 | V38: 0 | AB38: 154 | AC38: 115 | AD38: 1000 | AM38: 21 | AN38: =AM38*8.4 -> 176.4 | AO38: =AM38-AQ38-AR38 -> 21 | AP38: =AO38*8.4 -> 176.4 | AQ38: 0 | AR38: 0
A39: 69 | B39: 304603590 | C39: Z26424 | D39: Alexander Jouravski | E39: 2160 | F39: Fulltime Employee | G39: Active | H39: 44794 | J39: 648240 | L39: =J39/12*70% -> 37814 | M39: =J39/12*30% -> 16206 | N39: =SUM(L39:M39) -> 54020 | O39: 15 | P39: =(N39+W39+X39+AA39+T39+R39)*O39% -> 8103 | S39: 315 | V39: 0 | AB39: 154 | AC39: 115 | AD39: 1000 | AM39: 21 | AN39: =AM39*8.4 -> 176.4 | AO39: =AM39-AQ39-AR39 -> 21 | AP39: =AO39*8.4 -> 176.4 | AQ39: 0 | AR39: 0
A40: 76 | B40: 39076492 | C40: Z26527 | D40: Roi Zentner | E40: 2885 | F40: Fulltime Employee | G40: Active | H40: 44805 | J40: 551655 | L40: =J40/12*70% -> 32179.875 | M40: =J40/12*30% -> 13791.375 | N40: =SUM(L40:M40) -> 45971.25 | O40: 15 | P40: =(N40+W40+X40+AA40+T40+R40)*O40% -> 6895.6875 | S40: 315 | V40: 0 | AB40: 154 | AC40: 115 | AD40: 985.3 | AM40: 21 | AN40: =AM40*8.4 -> 176.4 | AO40: =AM40-AQ40-AR40 -> 20 | AP40: =AO40*8.4 -> 168 | AQ40: 1 | AR40: 0 | AU40: 350
A41: 71 | B41: 207866625 | C41: Z26792 | D41: Roee Gozlan | E41: 2885 | F41: Parttime Employee 50% working position | G41: Active | H41: 44805 | J41: 233617.65 | K41: Parttime Employee 50% working position | L41: =J41/12*70% -> 13627.696 | M41: =J41/12*30% -> 5840.4412 | N41: =SUM(L41:M41) -> 19468.137 | O41: 15 | P41: =(N41+W41+X41+AA41+T41+R41)*O41% -> 2920.2206 | S41: 315 | V41: 0 | AB41: 154 | AC41: 115 | AD41: 5 | AM41: 21 | AN41: =AM41*8.4 -> 176.4 | AO41: =AM41-AQ41-AR41 -> 21 | AP41: =AO41*8.4 -> 176.4 | AQ41: 0 | AR41: 0
A42: 77 | B42: 25197153 | C42: Z26528 | D42: Shahar Inbar | E42: 2160 | F42: Fulltime Employee | G42: Active | H42: 44805 | J42: 656000 | L42: =J42/12*70% -> 38266.667 | M42: =J42/12*30% -> 16400 | N42: =SUM(L42:M42) -> 54666.667 | O42: 10 | P42: =(N42+W42+X42+AA42+T42+R42)*O42% -> 5466.6667 | S42: 315 | V42: 0 | AB42: 154 | AC42: 115 | AD42: 997 | AM42: 21 | AN42: =AM42*8.4 -> 176.4 | AO42: =AM42-AQ42-AR42 -> 8 | AP42: =AO42*8.4 -> 67.2 | AQ42: 13 | AR42: 0 | AU42: 100
A43: 74 | B43: 316462597 | C43: Z26575 | D43: Reuven Abramov | E43: 2160 | F43: Fulltime Employee | G43: Active | H43: 44805 | J43: 403082 | L43: =J43/12*70% -> 23513.117 | M43: =J43/12*30% -> 10077.05 | N43: =SUM(L43:M43) -> 33590.167 | O43: 15 | P43: =(N43+W43+X43+AA43+T43+R43)*O43% -> 5038.525 | S43: 315 | V43: 0 | AB43: 154 | AC43: 115 | AD43: 999.27 | AM43: 21 | AN43: =AM43*8.4 -> 176.4 | AO43: =AM43-AQ43-AR43 -> 21 | AP43: =AO43*8.4 -> 176.4 | AQ43: 0 | AR43: 0
A44: 70 | B44: 43163146 | C44: Z26531 | D44: Sagie Vachman | E44: 2410 | F44: Fulltime Employee | G44: Active | H44: 44808 | J44: 616240 | L44: =J44/12*70% -> 35947.333 | M44: =J44/12*30% -> 15406 | N44: =SUM(L44:M44) -> 51353.333 | O44: 10 | P44: =(N44+W44+X44+AA44+T44+R44)*O44% -> 5135.3333 | S44: 315 | V44: 0 | AB44: 154 | AC44: 115 | AD44: 830.78 | AM44: 21 | AN44: =AM44*8.4 -> 176.4 | AO44: =AM44-AQ44-AR44 -> 21 | AP44: =AO44*8.4 -> 176.4 | AQ44: 0 | AR44: 0
A45: 72 | B45: 28831709 | C45: Z26533 | D45: Assaf Almaz | E45: 2160 | F45: Fulltime Employee | G45: Active | H45: 44809 | J45: 1060582.6 | L45: =J45/12*70% -> 61867.321 | M45: =J45/12*30% -> 26514.566 | N45: =SUM(L45:M45) -> 88381.887 | O45: 10 | P45: =(N45+W45+X45+AA45+T45+R45)*O45% -> 8838.1887 | S45: 315 | V45: 0 | AB45: 154 | AC45: 115 | AD45: 0 | AM45: 21 | AN45: =AM45*8.4 -> 176.4 | AO45: =AM45-AQ45-AR45 -> 21 | AP45: =AO45*8.4 -> 176.4 | AQ45: 0 | AR45: 0
A46: 73 | B46: 38553186 | C46: Z26629 | D46: Assaf Nir | E46: 2160 | F46: Fulltime Employee | G46: Active | H46: 44815 | J46: 667000 | L46: =J46/12*70% -> 38908.333 | M46: =J46/12*30% -> 16675 | N46: =SUM(L46:M46) -> 55583.333 | O46: 14 | P46: =(N46+W46+X46+AA46+T46+R46)*O46% -> 7781.6667 | S46: 315 | V46: 0 | AB46: 154 | AC46: 115 | AD46: 1000 | AM46: 21 | AN46: =AM46*8.4 -> 176.4 | AO46: =AM46-AQ46-AR46 -> 20 | AP46: =AO46*8.4 -> 168 | AQ46: 1 | AR46: 0
A47: 78 | B47: 314829532 | C47: Z26711 | D47: Nir Barel | E47: 2885 | F47: Fulltime Employee | G47: Active | H47: 44822 | J47: 492808 | L47: =J47/12*70% -> 28747.133 | M47: =J47/12*30% -> 12320.2 | N47: =SUM(L47:M47) -> 41067.333 | O47: 15 | P47: =(N47+W47+X47+AA47+T47+R47)*O47% -> 6160.1 | S47: 315 | V47: 0 | AB47: 154 | AC47: 115 | AD47: 1000 | AM47: 21 | AN47: =AM47*8.4 -> 176.4 | AO47: =AM47-AQ47-AR47 -> 7 | AP47: =AO47*8.4 -> 58.8 | AQ47: 14 | AR47: 0
A48: 80 | B48: 304332992 | C48: Z26721 | D48: Ilya Rybak | E48: 2160 | F48: Fulltime Employee | G48: Active | H48: 44832 | J48: 718000 | L48: =J48/12*70% -> 41883.333 | M48: =J48/12*30% -> 17950 | N48: =SUM(L48:M48) -> 59833.333 | O48: 10 | P48: =(N48+W48+X48+AA48+T48+R48)*O48% -> 5983.3333 | S48: 315 | V48: 0 | AB48: 154 | AC48: 115 | AD48: 999.9 | AM48: 21 | AN48: =AM48*8.4 -> 176.4 | AO48: =AM48-AQ48-AR48 -> 21 | AP48: =AO48*8.4 -> 176.4 | AQ48: 0 | AR48: 0
A49: 81 | B49: 33574153 | C49: Z27233 | D49: Guy Gurfinkel | E49: 2160 | F49: Fulltime Employee | G49: Active | H49: 44847 | J49: 752000 | L49: =J49/12*70% -> 43866.667 | M49: =J49/12*30% -> 18800 | N49: =SUM(L49:M49) -> 62666.667 | O49: 10 | P49: =(N49+W49+X49+AA49+T49+R49)*O49% -> 6266.6667 | S49: 315 | V49: 0 | AB49: 154 | AC49: 115 | AD49: 994 | AM49: 21 | AN49: =AM49*8.4 -> 176.4 | AO49: =AM49-AQ49-AR49 -> 21 | AP49: =AO49*8.4 -> 176.4 | AQ49: 0 | AR49: 0 | AU49: 300
A50: 82 | B50: 22992150 | C50: Z26885 | D50: Hovav Bornstein (Chovav) | E50: 2540 | F50: Fulltime Employee | G50: Active | H50: 44852 | J50: 850731.9 | L50: =J50/12*70% -> 49626.027 | M50: =J50/12*30% -> 21268.297 | N50: =SUM(L50:M50) -> 70894.325 | O50: 10 | P50: =(N50+W50+X50+AA50+T50+R50)*O50% -> 7089.4325 | S50: 315 | V50: 0 | AB50: 154 | AC50: 115 | AD50: 994.68 | AM50: 21 | AN50: =AM50*8.4 -> 176.4 | AO50: =AM50-AQ50-AR50 -> 21 | AP50: =AO50*8.4 -> 176.4 | AQ50: 0 | AR50: 0
A51: 83 | B51: 34273748 | C51: Z26886 | D51: Moshe Yuda | E51: 2160 | F51: Fulltime Employee | G51: Active | H51: 44857 | J51: 670720 | L51: =J51/12*70% -> 39125.333 | M51: =J51/12*30% -> 16768 | N51: =SUM(L51:M51) -> 55893.333 | O51: 10 | P51: =(N51+W51+X51+AA51+T51+R51)*O51% -> 5589.3333 | S51: 315 | V51: 0 | AB51: 154 | AC51: 115 | AD51: 959.45 | AM51: 21 | AN51: =AM51*8.4 -> 176.4 | AO51: =AM51-AQ51-AR51 -> 20 | AP51: =AO51*8.4 -> 168 | AQ51: 1 | AR51: 0
A52: 84 | B52: 11629599 | C52: Z27260 | D52: Shmulik Rozenzweig | E52: 2400 | F52: Fulltime Employee | G52: Active | H52: 44870 | J52: 667647.36 | L52: =J52/12*70% -> 38946.096 | M52: =J52/12*30% -> 16691.184 | N52: =SUM(L52:M52) -> 55637.28 | O52: 10 | P52: =(N52+W52+X52+AA52+T52+R52)*O52% -> 5563.728 | S52: 315 | V52: 0 | AB52: 154 | AC52: 115 | AD52: 998.85 | AM52: 21 | AN52: =AM52*8.4 -> 176.4 | AO52: =AM52-AQ52-AR52 -> 21 | AP52: =AO52*8.4 -> 176.4 | AQ52: 0 | AR52: 0
A53: 85 | B53: 27161900 | C53: Z26938 | D53: Assaf Cohen | E53: 2160 | F53: Fulltime Employee | G53: Active | H53: 44894 | J53: 648000 | L53: =J53/12*70% -> 37800 | M53: =J53/12*30% -> 16200 | N53: =SUM(L53:M53) -> 54000 | O53: 10 | P53: =(N53+W53+X53+AA53+T53+R53)*O53% -> 5400 | S53: 315 | V53: 0 | AB53: 154 | AC53: 115 | AD53: 1000 | AM53: 21 | AN53: =AM53*8.4 -> 176.4 | AO53: =AM53-AQ53-AR53 -> 20 | AP53: =AO53*8.4 -> 168 | AQ53: 1 | AR53: 0
A54: 86 | B54: 302753595 | C54: Z27264 | D54: Matanel Elhayani | E54: 2540 | F54: Fulltime Employee | G54: Active | H54: 44894 | J54: 751514 | L54: =J54/12*70% -> 43838.317 | M54: =J54/12*30% -> 18787.85 | N54: =SUM(L54:M54) -> 62626.167 | O54: 9 | P54: =(N54+W54+X54+AA54+T54+R54)*O54% -> 5636.355 | S54: 315 | V54: 0 | AB54: 154 | AC54: 115 | AD54: 1000 | AM54: 21 | AN54: =AM54*8.4 -> 176.4 | AO54: =AM54-AQ54-AR54 -> 11.5 | AP54: =AO54*8.4 -> 96.6 | AQ54: 9.5 | AR54: 0
A55: 87 | B55: 31409336 | C55: Z27551 | D55: Chen Dahan | E55: 2410 | F55: Fulltime Employee | G55: Active | H55: 44896 | J55: 308160 | L55: =J55/12*70% -> 17976 | M55: =J55/12*30% -> 7704 | N55: =SUM(L55:M55) -> 25680 | O55: 15 | P55: =(N55+W55+X55+AA55+T55+R55)*O55% -> 3852 | S55: 315 | V55: 0 | AB55: 154 | AC55: 115 | AD55: 999.1 | AM55: 21 | AN55: =AM55*8.4 -> 176.4 | AO55: =AM55-AQ55-AR55 -> 18 | AP55: =AO55*8.4 -> 151.2 | AQ55: 0 | AR55: 3
A56: 88 | B56: 35554019 | C56: Z27552 | D56: Amir Hazbani | E56: 4442 | F56: Fulltime Employee | G56: Active | H56: 44899 | J56: 561429 | L56: =J56/12*70% -> 32750.025 | M56: =J56/12*30% -> 14035.725 | N56: =SUM(L56:M56) -> 46785.75 | O56: 10 | P56: =(N56+W56+X56+AA56+T56+R56)*O56% -> 4678.575 | S56: 315 | V56: 0 | AB56: 154 | AC56: 115 | AD56: 998.89 | AM56: 21 | AN56: =AM56*8.4 -> 176.4 | AO56: =AM56-AQ56-AR56 -> 21 | AP56: =AO56*8.4 -> 176.4 | AQ56: 0 | AR56: 0
A57: 89 | B57: 32949166 | C57: Z28055 | D57: Oded Aharon | E57: 2160 | F57: Fulltime Employee | G57: Active | H57: 44986 | J57: 384000 | L57: =J57/12*70% -> 22400 | M57: =J57/12*30% -> 9600 | N57: =SUM(L57:M57) -> 32000 | O57: 0 | P57: =(N57+W57+X57+AA57+T57+R57)*O57% -> 0 | S57: 315 | V57: 0 | AB57: 154 | AC57: 115 | AD57: 999.69 | AM57: 21 | AN57: =AM57*8.4 -> 176.4 | AO57: =AM57-AQ57-AR57 -> 19 | AP57: =AO57*8.4 -> 159.6 | AQ57: 2 | AR57: 0
A58: 90 | B58: 206963159 | C58: Z30392 | D58: Omer Alon Aboudy | E58: 2192 | F58: Fulltime Employee | G58: Active | H58: 45088 | J58: 467376 | L58: =J58/12*70% -> 27263.6 | M58: =J58/12*30% -> 11684.4 | N58: =SUM(L58:M58) -> 38948 | O58: 15 | P58: =(N58+W58+X58+AA58+T58+R58)*O58% -> 5842.2 | S58: 315 | V58: 0 | AB58: 154 | AC58: 115 | AD58: 999.46 | AM58: 21 | AN58: =AM58*8.4 -> 176.4 | AO58: =AM58-AQ58-AR58 -> 21 | AP58: =AO58*8.4 -> 176.4 | AQ58: 0 | AR58: 0
A59: 94 | B59: 23648884 | C59: Z31362 | D59: Meir Mouly | E59: 2160 | F59: Fulltime Employee | G59: Active | H59: 45259 | J59: 468000 | L59: =J59/12*70% -> 27300 | M59: =J59/12*30% -> 11700 | N59: =SUM(L59:M59) -> 39000 | O59: 15 | P59: =(N59+W59+X59+AA59+T59+R59)*O59% -> 5850 | S59: 315 | V59: 0 | AB59: 154 | AC59: 115 | AD59: 995.55 | AM59: 21 | AN59: =AM59*8.4 -> 176.4 | AO59: =AM59-AQ59-AR59 -> 21 | AP59: =AO59*8.4 -> 176.4 | AQ59: 0 | AR59: 0
A60: 96 | B60: 36573137 | C60: Z31513 | D60: Gal Peled | E60: 2250 | F60: Fulltime Employee | G60: Active | H60: 45263 | J60: 432000 | L60: =J60/12*70% -> 25200 | M60: =J60/12*30% -> 10800 | N60: =SUM(L60:M60) -> 36000 | O60: 15 | P60: =(N60+W60+X60+AA60+T60+R60)*O60% -> 5400 | S60: 315 | V60: 0 | AB60: 154 | AC60: 115 | AD60: 1000 | AM60: 21 | AN60: =AM60*8.4 -> 176.4 | AO60: =AM60-AQ60-AR60 -> 20 | AP60: =AO60*8.4 -> 168 | AQ60: 1 | AR60: 0
A61: 95 | B61: 306323411 | C61: Z31214 | D61: Alexander Kipnis | E61: 2160 | F61: Fulltime Employee | G61: Active | H61: 45263 | J61: 685680 | L61: =J61/12*70% -> 39998 | M61: =J61/12*30% -> 17142 | N61: =SUM(L61:M61) -> 57140 | O61: 15 | P61: =(N61+W61+X61+AA61+T61+R61)*O61% -> 8571 | S61: 315 | V61: 0 | AB61: 154 | AC61: 115 | AD61: 902.15 | AM61: 21 | AN61: =AM61*8.4 -> 176.4 | AO61: =AM61-AQ61-AR61 -> 21 | AP61: =AO61*8.4 -> 176.4 | AQ61: 0 | AR61: 0 | AU61: 7758.37
A62: 97 | B62: 204697593 | C62: Z31705 | D62: Orel Shmueli | E62: 2180 | F62: Fulltime Employee | G62: Unpaid Leave | H62: 45284 | J62: 359923.2 | K62: Unpaid Leave from 14th Oct till 9th Dec 2025 | O62: 15 | P62: =(N62+W62+X62+AA62+T62+R62)*O62% -> 0 | V62: 0 | AD62: 827.26 | AM62: 21 | AN62: =AM62*8.4 -> 176.4 | AO62: =AM62-AQ62-AR62 -> 21 | AP62: =AO62*8.4 -> 176.4 | AQ62: 0 | AR62: 0
A63: 98 | B63: 306540816 | C63: Z31926 | D63: Alex Mulman | E63: 1608 | F63: Fulltime Employee | G63: Active | H63: 45305 | J63: 305510.4 | L63: =J63/12*70% -> 17821.44 | M63: =J63/12*30% -> 7637.76 | N63: =SUM(L63:M63) -> 25459.2 | O63: 7 | P63: =(N63+W63+X63+AA63+T63+R63)*O63% -> 1782.144 | S63: 315 | V63: 0 | AB63: 154 | AC63: 115 | AD63: 999.49 | AM63: 21 | AN63: =AM63*8.4 -> 176.4 | AO63: =AM63-AQ63-AR63 -> 20 | AP63: =AO63*8.4 -> 168 | AQ63: 0 | AR63: 1
A64: 99 | B64: 40794422 | C64: Z31821 | D64: Tamir Eliaz | E64: 1200 | F64: Fulltime Employee | G64: Active | H64: 45305 | J64: 594880 | L64: =J64/12*70% -> 34701.333 | M64: =J64/12*30% -> 14872 | N64: =SUM(L64:M64) -> 49573.333 | O64: 15 | P64: =(N64+W64+X64+AA64+T64+R64)*O64% -> 7436 | S64: 315 | V64: 0 | AB64: 154 | AC64: 115 | AD64: 998.25 | AM64: 21 | AN64: =AM64*8.4 -> 176.4 | AO64: =AM64-AQ64-AR64 -> 21 | AP64: =AO64*8.4 -> 176.4 | AQ64: 0 | AR64: 0 | AU64: 542.37
A65: 100 | B65: 305306482 | C65: Z31754 | D65: Gal Shitrit | E65: 2190 | F65: Fulltime Employee | G65: Active | H65: 45312 | J65: 448800 | L65: =J65/12*70% -> 26180 | M65: =J65/12*30% -> 11220 | N65: =SUM(L65:M65) -> 37400 | O65: 0 | P65: =(N65+W65+X65+AA65+T65+R65)*O65% -> 0 | S65: 315 | V65: 0 | AB65: 154 | AC65: 115 | AD65: 881.9 | AM65: 21 | AN65: =AM65*8.4 -> 176.4 | AO65: =AM65-AQ65-AR65 -> 21 | AP65: =AO65*8.4 -> 176.4 | AQ65: 0 | AR65: 0
A66: 105 | B66: 203080957 | C66: Z32029 | D66: Roei Amit | E66: 2160 | F66: Fulltime Employee | G66: Active | H66: 45354 | J66: 530400 | L66: =J66/12*70% -> 30940 | M66: =J66/12*30% -> 13260 | N66: =SUM(L66:M66) -> 44200 | O66: 15 | P66: =(N66+W66+X66+AA66+T66+R66)*O66% -> 6630 | S66: 315 | V66: 0 | AB66: 154 | AC66: 115 | AD66: 999.05 | AM66: 21 | AN66: =AM66*8.4 -> 176.4 | AO66: =AM66-AQ66-AR66 -> 19 | AP66: =AO66*8.4 -> 159.6 | AQ66: 0 | AR66: 2
A67: 102 | B67: 32112336 | C67: Z32526 | D67: Danny Shacham | E67: 2460 | F67: Fulltime Employee | G67: Active | H67: 45354 | J67: 959723.1 | L67: =J67/12*70% -> 55983.847 | M67: =J67/12*30% -> 23993.077 | N67: =SUM(L67:M67) -> 79976.925 | O67: 7 | P67: =(N67+W67+X67+AA67+T67+R67)*O67% -> 5598.3848 | S67: 315 | V67: 0 | AB67: 154 | AC67: 115 | AD67: 973.28 | AM67: 21 | AN67: =AM67*8.4 -> 176.4 | AO67: =AM67-AQ67-AR67 -> 21 | AP67: =AO67*8.4 -> 176.4 | AQ67: 0 | AR67: 0
A68: 101 | B68: 308911635 | C68: Z31989 | D68: Alex Korthny | E68: 2160 | F68: Fulltime Employee | G68: Active | H68: 45354 | J68: 681000 | L68: =J68/12*70% -> 39725 | M68: =J68/12*30% -> 17025 | N68: =SUM(L68:M68) -> 56750 | O68: 0 | P68: =(N68+W68+X68+AA68+T68+R68)*O68% -> 0 | S68: 315 | V68: 0 | AB68: 154 | AC68: 115 | AD68: 950.6 | AM68: 21 | AN68: =AM68*8.4 -> 176.4 | AO68: =AM68-AQ68-AR68 -> 21 | AP68: =AO68*8.4 -> 176.4 | AQ68: 0 | AR68: 0
A69: 103 | B69: 208207027 | C69: Z32464 | D69: Nati Abutbul | E69: 2885 | F69: Fulltime Employee | G69: Active | H69: 45375 | J69: 684000 | L69: =J69/12*70% -> 39900 | M69: =J69/12*30% -> 17100 | N69: =SUM(L69:M69) -> 57000 | O69: 13 | P69: =(N69+W69+X69+AA69+T69+R69)*O69% -> 7410 | S69: 315 | V69: 0 | AB69: 154 | AC69: 115 | AD69: 1000 | AM69: 21 | AN69: =AM69*8.4 -> 176.4 | AO69: =AM69-AQ69-AR69 -> 21 | AP69: =AO69*8.4 -> 176.4 | AQ69: 0 | AR69: 0
A70: 104 | B70: 201179025 | C70: Z32650 | D70: Sela Oren | E70: 2160 | F70: Fulltime Employee | G70: Active | H70: 45375 | J70: 474422.4 | L70: =J70/12*70% -> 27674.64 | M70: =J70/12*30% -> 11860.56 | N70: =SUM(L70:M70) -> 39535.2 | O70: 15 | P70: =(N70+W70+X70+AA70+T70+R70)*O70% -> 5930.28 | S70: 315 | V70: 0 | AB70: 154 | AC70: 115 | AD70: 998.22 | AM70: 21 | AN70: =AM70*8.4 -> 176.4 | AO70: =AM70-AQ70-AR70 -> 21 | AP70: =AO70*8.4 -> 176.4 | AQ70: 0 | AR70: 0 | AU70: 100
A71: 106 | B71: 300759842 | C71: Z32871 | D71: Elhanan Mizrahi | E71: 2885 | F71: Fulltime Employee | G71: Active | H71: 45396 | J71: 504000 | L71: =J71/12*70% -> 29400 | M71: =J71/12*30% -> 12600 | N71: =SUM(L71:M71) -> 42000 | O71: 12 | P71: =(N71+W71+X71+AA71+T71+R71)*O71% -> 5040 | S71: 315 | V71: 0 | AB71: 154 | AC71: 115 | AD71: 1000 | AM71: 21 | AN71: =AM71*8.4 -> 176.4 | AO71: =AM71-AQ71-AR71 -> 21 | AP71: =AO71*8.4 -> 176.4 | AQ71: 0 | AR71: 0
A72: 108 | B72: 36193886 | C72: Z33155 | D72: Arik Sher | E72: 2410 | F72: Fulltime Employee | G72: Active | H72: 45403 | J72: 599040 | L72: =J72/12*70% -> 34944 | M72: =J72/12*30% -> 14976 | N72: =SUM(L72:M72) -> 49920 | O72: 15 | P72: =(N72+W72+X72+AA72+T72+R72)*O72% -> 7488 | S72: 315 | V72: 0 | AB72: 154 | AC72: 115 | AD72: 999.99 | AM72: 21 | AN72: =AM72*8.4 -> 176.4 | AO72: =AM72-AQ72-AR72 -> 21 | AP72: =AO72*8.4 -> 176.4 | AQ72: 0 | AR72: 0
A73: 107 | B73: 315670182 | C73: Z33156 | D73: Pnina Yonayov | E73: 2450 | F73: Fulltime Employee | G73: Active | H73: 45403 | J73: 378000 | L73: =J73/12*70% -> 22050 | M73: =J73/12*30% -> 9450 | N73: =SUM(L73:M73) -> 31500 | O73: 15 | P73: =(N73+W73+X73+AA73+T73+R73)*O73% -> 4725 | S73: 315 | V73: 150 | AB73: 154 | AC73: 115 | AD73: 999.6 | AM73: 21 | AN73: =AM73*8.4 -> 176.4 | AO73: =AM73-AQ73-AR73 -> 21 | AP73: =AO73*8.4 -> 176.4 | AQ73: 0 | AR73: 0
A74: 109 | B74: 311492110 | C74: Z33385 | D74: Ori Netanel Ben Zaken | E74: 2410 | F74: Fulltime Employee | G74: Active | H74: 45473 | J74: 534240 | L74: =J74/12*70% -> 31164 | M74: =J74/12*30% -> 13356 | N74: =SUM(L74:M74) -> 44520 | O74: 0 | P74: =(N74+W74+X74+AA74+T74+R74)*O74% -> 0 | S74: 315 | V74: 0 | AB74: 154 | AC74: 115 | AD74: 1000 | AM74: 21 | AN74: =AM74*8.4 -> 176.4 | AO74: =AM74-AQ74-AR74 -> 16 | AP74: =AO74*8.4 -> 134.4 | AQ74: 5 | AR74: 0 | AU74: 354
A75: 111 | B75: 301380788 | C75: Z28401 | D75: Alon Rosenblum | E75: 2192 | F75: Fulltime Employee | G75: Active | H75: 44977 | J75: 562432 | L75: =J75/12*70% -> 32808.533 | M75: =J75/12*30% -> 14060.8 | N75: =SUM(L75:M75) -> 46869.333 | O75: 15 | P75: =(N75+W75+X75+AA75+T75+R75)*O75% -> 7030.4 | S75: 315 | V75: 0 | AB75: 154 | AC75: 115 | AD75: 1000 | AM75: 21 | AN75: =AM75*8.4 -> 176.4 | AO75: =AM75-AQ75-AR75 -> 21 | AP75: =AO75*8.4 -> 176.4 | AQ75: 0 | AR75: 0
A76: 112 | B76: 300885258 | C76: Z28402 | D76: Barak Haver | E76: 2192 | F76: Fulltime Employee | G76: Active | H76: 44977 | J76: 592300 | L76: =J76/12*70% -> 34550.833 | M76: =J76/12*30% -> 14807.5 | N76: =SUM(L76:M76) -> 49358.333 | O76: 13 | P76: =(N76+W76+X76+AA76+T76+R76)*O76% -> 6416.5833 | S76: 315 | V76: 0 | AB76: 154 | AC76: 115 | AD76: 999.9 | AM76: 21 | AN76: =AM76*8.4 -> 176.4 | AO76: =AM76-AQ76-AR76 -> 20.5 | AP76: =AO76*8.4 -> 172.2 | AQ76: 0.5 | AR76: 0
A77: 113 | B77: 306555863 | C77: Z28404 | D77: Boris Gorin | E77: 2540 | F77: Fulltime Employee | G77: Active | H77: 44977 | J77: 752103 | L77: =J77/12*70% -> 43872.675 | M77: =J77/12*30% -> 18802.575 | N77: =SUM(L77:M77) -> 62675.25 | O77: 15 | P77: =(N77+W77+X77+AA77+T77+R77)*O77% -> 9401.2875 | S77: 315 | V77: 150 | AB77: 154 | AC77: 115 | AD77: 1000 | AM77: 21 | AN77: =AM77*8.4 -> 176.4 | AO77: =AM77-AQ77-AR77 -> 21 | AP77: =AO77*8.4 -> 176.4 | AQ77: 0 | AR77: 0 | AU77: 14397.78
A78: 114 | B78: 334064102 | C78: Z28405 | D78: Carlos Dorin | E78: 2192 | F78: Fulltime Employee | G78: Active | H78: 44977 | J78: 391910.4 | L78: =J78/12*70% -> 22861.44 | M78: =J78/12*30% -> 9797.76 | N78: =SUM(L78:M78) -> 32659.2 | O78: 2 | P78: =(N78+W78+X78+AA78+T78+R78)*O78% -> 653.184 | S78: 315 | V78: 0 | AB78: 154 | AC78: 115 | AD78: 992.09 | AM78: 21 | AN78: =AM78*8.4 -> 176.4 | AO78: =AM78-AQ78-AR78 -> 21 | AP78: =AO78*8.4 -> 176.4 | AQ78: 0 | AR78: 0
A79: 115 | B79: 208754812 | C79: Z28407 | D79: Dalia Wolf | E79: 2540 | F79: Fulltime Employee | G79: Active | H79: 44977 | J79: 377711 | L79: =J79/12*70% -> 22033.142 | M79: =J79/12*30% -> 9442.775 | N79: =SUM(L79:M79) -> 31475.917 | O79: 15 | P79: =(N79+W79+X79+AA79+T79+R79)*O79% -> 4721.3875 | S79: 315 | V79: 0 | AB79: 154 | AC79: 115 | AD79: 1000 | AM79: 21 | AN79: =AM79*8.4 -> 176.4 | AO79: =AM79-AQ79-AR79 -> 18.5 | AP79: =AO79*8.4 -> 155.4 | AQ79: 2.5 | AR79: 0
A80: 117 | B80: 200338424 | C80: Z28409 | D80: Gal Stainfeld | E80: 2192 | F80: Fulltime Employee | G80: Active | H80: 44977 | J80: 571980 | L80: =J80/12*70% -> 33365.5 | M80: =J80/12*30% -> 14299.5 | N80: =SUM(L80:M80) -> 47665 | O80: 15 | P80: =(N80+W80+X80+AA80+T80+R80)*O80% -> 7149.75 | S80: 315 | V80: 0 | AB80: 154 | AC80: 115 | AD80: 1000 | AM80: 21 | AN80: =AM80*8.4 -> 176.4 | AO80: =AM80-AQ80-AR80 -> 21 | AP80: =AO80*8.4 -> 176.4 | AQ80: 0 | AR80: 0 | AU80: 552
A81: 119 | B81: 302223573 | C81: Z28412 | D81: Lee Ben David | E81: 2540 | F81: Fulltime Employee | G81: Active | H81: 44977 | J81: 397555 | L81: =J81/12*70% -> 23190.708 | M81: =J81/12*30% -> 9938.875 | N81: =SUM(L81:M81) -> 33129.583 | O81: 15 | P81: =(N81+W81+X81+AA81+T81+R81)*O81% -> 4969.4375 | S81: 315 | V81: 0 | AB81: 154 | AC81: 115 | AD81: 999.1 | AM81: 21 | AN81: =AM81*8.4 -> 176.4 | AO81: =AM81-AQ81-AR81 -> 19 | AP81: =AO81*8.4 -> 159.6 | AQ81: 2 | AR81: 0
A82: 122 | B82: 34722355 | C82: Z28415 | D82: Niv Steingarten | E82: 2192 | F82: Fulltime Employee | G82: Active | H82: 44977 | J82: 747060 | L82: =J82/12*70% -> 43578.5 | M82: =J82/12*30% -> 18676.5 | N82: =SUM(L82:M82) -> 62255 | O82: 0 | P82: =(N82+W82+X82+AA82+T82+R82)*O82% -> 0 | S82: 315 | V82: 0 | AB82: 154 | AC82: 115 | AD82: 1000 | AM82: 21 | AN82: =AM82*8.4 -> 176.4 | AO82: =AM82-AQ82-AR82 -> 21 | AP82: =AO82*8.4 -> 176.4 | AQ82: 0 | AR82: 0
A83: 127 | B83: 209525047 | C83: Z28417 | D83: Shaked Cohen | E83: 1580 | F83: Fulltime Employee | G83: Active | H83: 44977 | J83: 161965.44 | L83: =J83/12*70% -> 9447.984 | M83: =J83/12*30% -> 4049.136 | N83: =SUM(L83:M83) -> 13497.12 | O83: 15 | P83: =(N83+W83+X83+AA83+T83+R83)*O83% -> 2024.568 | S83: 315 | V83: 0 | AB83: 154 | AC83: 115 | AD83: 995.9 | AM83: 21 | AN83: =AM83*8.4 -> 176.4 | AO83: =AM83-AQ83-AR83 -> 20 | AP83: =AO83*8.4 -> 168 | AQ83: 0 | AR83: 1
A84: 123 | B84: 209511500 | C84: Z28418 | D84: Shira Shatner | E84: 2192 | F84: Parttime Employee 40% working position | G84: Active | H84: 44977 | J84: 118260.48 | K84: Parttime Employee 40% working position | L84: =J84/12*70% -> 6898.528 | M84: =J84/12*30% -> 2956.512 | N84: =SUM(L84:M84) -> 9855.04 | O84: 0 | P84: =(N84+W84+X84+AA84+T84+R84)*O84% -> 0 | S84: 315 | V84: 0 | AB84: 154 | AC84: 115 | AD84: 699.59 | AM84: 21 | AN84: =AM84*8.4 -> 176.4 | AO84: =AM84-AQ84-AR84 -> 21 | AP84: =AO84*8.4 -> 176.4 | AQ84: 0 | AR84: 0
A85: 124 | B85: 66449257 | C85: Z28419 | D85: Tal Ohayon | E85: 2192 | F85: Fulltime Employee | G85: Active | H85: 44977 | J85: 534774.45 | L85: =J85/12*70% -> 31195.176 | M85: =J85/12*30% -> 13369.361 | N85: =SUM(L85:M85) -> 44564.537 | O85: 0 | P85: =(N85+W85+X85+AA85+T85+R85)*O85% -> 0 | S85: 315 | V85: 0 | AB85: 154 | AC85: 115 | AD85: 996.77 | AM85: 21 | AN85: =AM85*8.4 -> 176.4 | AO85: =AM85-AQ85-AR85 -> 21 | AP85: =AO85*8.4 -> 176.4 | AQ85: 0 | AR85: 0
A86: 125 | B86: 318183969 | C86: Z28420 | D86: Yuval Sadon | E86: 2540 | F86: Fulltime Employee | G86: Active | H86: 44977 | J86: 357447 | L86: =J86/12*70% -> 20851.075 | M86: =J86/12*30% -> 8936.175 | N86: =SUM(L86:M86) -> 29787.25 | O86: 15 | P86: =(N86+W86+X86+AA86+T86+R86)*O86% -> 4468.0875 | S86: 315 | V86: 0 | AB86: 154 | AC86: 115 | AD86: 807.37 | AM86: 21 | AN86: =AM86*8.4 -> 176.4 | AO86: =AM86-AQ86-AR86 -> 17 | AP86: =AO86*8.4 -> 142.8 | AQ86: 4 | AR86: 0
A87: 128 | B87: 303998116 | C87: Z33430 | D87: Evgheneii Bruter | E87: 2160 | F87: Fulltime Employee | G87: Active | H87: 45505 | J87: 702000 | L87: =J87/12*70% -> 40950 | M87: =J87/12*30% -> 17550 | N87: =SUM(L87:M87) -> 58500 | O87: 10 | P87: =(N87+W87+X87+AA87+T87+R87)*O87% -> 5850 | S87: 315 | V87: 0 | AB87: 154 | AC87: 115 | AD87: 999.49 | AM87: 21 | AN87: =AM87*8.4 -> 176.4 | AO87: =AM87-AQ87-AR87 -> 21 | AP87: =AO87*8.4 -> 176.4 | AQ87: 0 | AR87: 0
A88: 129 | B88: 203011200 | C88: Z33853 | D88: Ravit Rajuan | E88: 1150 | F88: Fulltime Employee | G88: Active | H88: 45557 | J88: 333720 | L88: =J88/12*70% -> 19467 | M88: =J88/12*30% -> 8343 | N88: =SUM(L88:M88) -> 27810 | O88: 0 | P88: =(N88+W88+X88+AA88+T88+R88)*O88% -> 0 | S88: 315 | V88: 0 | AB88: 154 | AC88: 115 | AD88: 999.34 | AM88: 21 | AN88: =AM88*8.4 -> 176.4 | AO88: =AM88-AQ88-AR88 -> 19 | AP88: =AO88*8.4 -> 159.6 | AQ88: 2 | AR88: 0
A89: 28 | B89: 318792538 | C89: Z23126 | D89: Tamir Leshetz | E89: 2410 | F89: Fulltime Employee | G89: Active | H89: 45606 | J89: 522000 | L89: =J89/12*70% -> 30450 | M89: =J89/12*30% -> 13050 | N89: =SUM(L89:M89) -> 43500 | O89: 15 | P89: =(N89+W89+X89+AA89+T89+R89)*O89% -> 6525 | S89: 315 | V89: 0 | AB89: 154 | AC89: 115 | AD89: 1000 | AM89: 21 | AN89: =AM89*8.4 -> 176.4 | AO89: =AM89-AQ89-AR89 -> 17 | AP89: =AO89*8.4 -> 142.8 | AQ89: 4 | AR89: 0
A90: 130 | B90: 310884036 | C90: Z34670 | D90: Yuval Adar | E90: 2250 | F90: Fulltime Employee | G90: Active | H90: 45613 | J90: 560000 | L90: =J90/12*70% -> 32666.667 | M90: =J90/12*30% -> 14000 | N90: =SUM(L90:M90) -> 46666.667 | O90: 0 | P90: =(N90+W90+X90+AA90+T90+R90)*O90% -> 0 | S90: 315 | V90: 0 | AB90: 154 | AC90: 115 | AD90: 1000 | AM90: 21 | AN90: =AM90*8.4 -> 176.4 | AO90: =AM90-AQ90-AR90 -> 20 | AP90: =AO90*8.4 -> 168 | AQ90: 0 | AR90: 1
A91: 132 | B91: 309640001 | C91: Z34513 | D91: Issahar Noam Gourfinkel | E91: 2160 | F91: Fulltime Employee | G91: Active | H91: 45641 | J91: 594000 | L91: =J91/12*70% -> 34650 | M91: =J91/12*30% -> 14850 | N91: =SUM(L91:M91) -> 49500 | O91: 0 | P91: =(N91+W91+X91+AA91+T91+R91)*O91% -> 0 | S91: 315 | V91: 0 | AB91: 154 | AC91: 115 | AD91: 1000 | AM91: 21 | AN91: =AM91*8.4 -> 176.4 | AO91: =AM91-AQ91-AR91 -> 21 | AP91: =AO91*8.4 -> 176.4 | AQ91: 0 | AR91: 0
A92: 133 | B92: 321175960 | C92: Z34866 | D92: Anael Ester Eisenschneider Buium | E92: 1200 | F92: Fulltime Employee | G92: Active | H92: 45669 | J92: 270000 | L92: =J92/12*70% -> 15750 | M92: =J92/12*30% -> 6750 | N92: =SUM(L92:M92) -> 22500 | O92: 0 | P92: =(N92+W92+X92+AA92+T92+R92)*O92% -> 0 | S92: 315 | V92: 0 | AB92: 154 | AC92: 115 | AD92: 1000 | AM92: 21 | AN92: =AM92*8.4 -> 176.4 | AO92: =AM92-AQ92-AR92 -> 19 | AP92: =AO92*8.4 -> 159.6 | AQ92: 0 | AR92: 2
A93: 134 | B93: 307101568 | C93: Z35164 | D93: Vadim Gurevich | E93: 2192 | F93: Fulltime Employee | G93: Active | H93: 45718 | J93: 550800 | L93: =J93/12*70% -> 32130 | M93: =J93/12*30% -> 13770 | N93: =SUM(L93:M93) -> 45900 | O93: 15 | P93: =(N93+W93+X93+AA93+T93+R93)*O93% -> 6885 | S93: 315 | V93: 0 | AB93: 154 | AC93: 115 | AD93: 879.31 | AM93: 21 | AN93: =AM93*8.4 -> 176.4 | AO93: =AM93-AQ93-AR93 -> 20 | AP93: =AO93*8.4 -> 168 | AQ93: 0 | AR93: 1
A94: 135 | B94: 32223067 | C94: Z36828 | D94: Aviram Sagiv | E94: 2160 | F94: Fulltime Employee | G94: Active | H94: 45802 | J94: 675000 | L94: =J94/12*70% -> 39375 | M94: =J94/12*30% -> 16875 | N94: =SUM(L94:M94) -> 56250 | O94: 15 | P94: =(N94+W94+X94+AA94+T94+R94)*O94% -> 8437.5 | S94: 315 | V94: 0 | AB94: 154 | AC94: 115 | AD94: 999.9 | AM94: 21 | AN94: =AM94*8.4 -> 176.4 | AO94: =AM94-AQ94-AR94 -> 18 | AP94: =AO94*8.4 -> 151.2 | AQ94: 3 | AR94: 0
A95: 136 | B95: 204209688 | C95: Z37196 | D95: Liron Nahshon | E95: 2160 | F95: Fulltime Employee | G95: Active | H95: 45851 | J95: 384000 | L95: =J95/12*70% -> 22400 | M95: =J95/12*30% -> 9600 | N95: =SUM(L95:M95) -> 32000 | O95: 0 | P95: =(N95+W95+X95+AA95+T95+R95)*O95% -> 0 | S95: 315 | V95: 0 | AB95: 154 | AC95: 115 | AD95: 1000 | AM95: 21 | AN95: =AM95*8.4 -> 176.4 | AO95: =AM95-AQ95-AR95 -> 21 | AP95: =AO95*8.4 -> 176.4 | AQ95: 0 | AR95: 0
A96: 137 | B96: 200448454 | C96: Z37169 | D96: Guy Castel | E96: 2192 | F96: Fulltime Employee | G96: Active | H96: 45851 | J96: 504000 | L96: =J96/12*70% -> 29400 | M96: =J96/12*30% -> 12600 | N96: =SUM(L96:M96) -> 42000 | O96: 0 | P96: =(N96+W96+X96+AA96+T96+R96)*O96% -> 0 | S96: 315 | V96: 0 | AB96: 154 | AC96: 115 | AD96: 1000 | AM96: 21 | AN96: =AM96*8.4 -> 176.4 | AO96: =AM96-AQ96-AR96 -> 21 | AP96: =AO96*8.4 -> 176.4 | AQ96: 0 | AR96: 0 | AU96: 53.9
A97: 138 | B97: 208543397 | C97: Z38899 | D97: Barak Valzer | E97: 2160 | F97: Fulltime Employee | G97: Active | H97: 45956 | J97: 498000 | L97: =J97/12*70% -> 29050 | M97: =J97/12*30% -> 12450 | N97: =SUM(L97:M97) -> 41500 | O97: 0 | P97: =(N97+W97+X97+AA97+T97+R97)*O97% -> 0 | S97: 315 | V97: 0 | AB97: 154 | AC97: 115 | AD97: 769 | AM97: 21 | AN97: =AM97*8.4 -> 176.4 | AO97: =AM97-AQ97-AR97 -> 21 | AP97: =AO97*8.4 -> 176.4 | AQ97: 0 | AR97: 0
A98: 139 | B98: 201383791 | C98: Z38808 | D98: Liat Soler | E98: 1110 | F98: Fulltime Employee | G98: Active, New Hire | H98: 45963 | J98: 285000 | K98: New Hire, No salary proration required | L98: =J98/12*70% -> 16625 | M98: =J98/12*30% -> 7125 | N98: =SUM(L98:M98) -> 23750 | O98: 0 | P98: =(N98+W98+X98+AA98+T98+R98)*O98% -> 0 | S98: 315 | AB98: 154 | AC98: 115 | AD98: 0 | AM98: 21 | AN98: =AM98*8.4 -> 176.4 | AO98: =AM98-AQ98-AR98 -> 21 | AP98: =AO98*8.4 -> 176.4 | AQ98: 0 | AR98: 0
E100: =SUM(E2:E99) -> 223875 | J100: =SUM(J2:J99) -> 52884257 | L100: =SUM(L2:L99) -> 3063919.5 | M100: =SUM(M2:M99) -> 1313108.3 | N100: =SUM(N2:N99) -> 4377027.8 | O100: =SUM(O2:O99) -> 1005 | P100: =SUM(P2:P99) -> 462665.62 | Q100: =SUM(Q2:Q99) -> 0 | R100: =SUM(R2:R99) -> 0 | S100: =SUM(S2:S99) -> 30240 | ... AV100: =SUM(AV2:AV99) -> 0

Sheet System
A1: שם החברה | B1: שנת מס | C1: מספר עובד | D1: שם העובד | E1: מספר חודש | F1: מספר רכיב | G1: שם רכיב שכר | H1: סיכום ברוטו | I1: סיכום כמות | J1: שם מחלקה
A2: זיסקיילר ישראל בע"מ | B2: 2025 | C2: 4 | D2: גלדין לאוניד | E2: 11 | F2: 1 | G2: משכורת | H2: 36763.43 | I2: 0 | J2: R&D
A3: זיסקיילר ישראל בע"מ | B3: 2025 | C3: 4 | D3: גלדין לאוניד | E3: 11 | F3: 3 | G3: טלפון | H3: 230 | I3: 0 | J3: R&D
A4: זיסקיילר ישראל בע"מ | B4: 2025 | C4: 4 | D4: גלדין לאוניד | E4: 11 | F4: 4 | G4: נסיעות | H4: 315 | I4: 0 | J4: R&D
A5: זיסקיילר ישראל בע"מ | B5: 2025 | C5: 4 | D5: גלדין לאוניד | E5: 11 | F5: 6 | G5: ש.נ גלובליות | H5: 15755.76 | I5: 0 | J5: R&D
A6: זיסקיילר ישראל בע"מ | B6: 2025 | C6: 4 | D6: גלדין לאוניד | E6: 11 | F6: 24 | G6: שווי ארוחות | H6: 1000 | I6: 0 | J6: R&D
A7: זיסקיילר ישראל בע"מ | B7: 2025 | C7: 4 | D7: גלדין לאוניד | E7: 11 | F7: 25 | G7: פיצוי שווי | H7: 154 | I7: 0 | J7: R&D
A8: זיסקיילר ישראל בע"מ | B8: 2025 | C8: 4 | D8: גלדין לאוניד | E8: 11 | F8: 51 | G8: שווי ביטוח בריאות | H8: 154 | I8: 0 | J8: R&D
A9: זיסקיילר ישראל בע"מ | B9: 2025 | C9: 4 | D9: גלדין לאוניד | E9: 11 | F9: 93 | G9: זק.תגמולים | H9: 1616.85 | I9: 0 | J9: R&D
A10: זיסקיילר ישראל בע"מ | B10: 2025 | C10: 6 | D10: פוזמנטיר נדב | E10: 11 | F10: 1 | G10: משכורת | H10: 36458.74 | I10: 0 | J10: R&D
A11: זיסקיילר ישראל בע"מ | B11: 2025 | C11: 6 | D11: פוזמנטיר נדב | E11: 11 | F11: 3 | G11: טלפון | H11: 230 | I11: 0 | J11: R&D
A12: זיסקיילר ישראל בע"מ | B12: 2025 | C12: 6 | D12: פוזמנטיר נדב | E12: 11 | F12: 4 | G12: נסיעות | H12: 315 | I12: 0 | J12: R&D
A13: זיסקיילר ישראל בע"מ | B13: 2025 | C13: 6 | D13: פוזמנטיר נדב | E13: 11 | F13: 6 | G13: ש.נ גלובליות | H13: 15625.18 | I13: 0 | J13: R&D
... A804: זיסקיילר ישראל בע"מ | B804: 2025 | C804: 139 | D804: סולר ליאת | E804: 11 | F804: 51 | G804: שווי ביטוח בריאות | H804: 154 | I804: 0 | J804: customer success

Sheet Deductions
A1: שם החברה | B1: שנת מס | C1: מספר עובד | D1: שם העובד | E1: שם מחלקה | F1: מספר חודש | G1: מספר שורה | H1: מספר ניכוי | I1: קוד סוג ניכוי | J1: שם הניכוי | K1: סכום הניכוי
A2: זיסקיילר ישראל בע"מ | B2: 2025 | C2: 4 | D2: גלדין לאוניד | E2: R&D | F2: 11 | G2: 0 | H2: 8 | I2: ש | J2: מקד' אופצ' | K2: 7877.88
A3: זיסקיילר ישראל בע"מ | B3: 2025 | C3: 4 | D3: גלדין לאוניד | E3: R&D | F3: 11 | G3: 1 | H3: 9 | I3: ש | J3: החזר הוצ' | K3: -1580
A4: זיסקיילר ישראל בע"מ | B4: 2025 | C4: 6 | D4: פוזמנטיר נדב | E4: R&D | F4: 11 | G4: 0 | H4: 8 | I4: ש | J4: מקד' אופצ' | K4: 7812.59
A5: זיסקיילר ישראל בע"מ | B5: 2025 | C5: 8 | D5: כץ עידו | E5: R&D | F5: 11 | G5: 0 | H5: 8 | I5: ש | J5: מקד' אופצ' | K5: 7650.03
A6: זיסקיילר ישראל בע"מ | B6: 2025 | C6: 8 | D6: כץ עידו | E6: R&D | F6: 11 | G6: 1 | H6: 9 | I6: ש | J6: החזר הוצ' | K6: -1860
A7: זיסקיילר ישראל בע"מ | B7: 2025 | C7: 11 | D7: קולברג אלעד | E7: R&D | F7: 11 | G7: 0 | H7: 8 | I7: ש | J7: מקד' אופצ' | K7: 6126.68
A8: זיסקיילר ישראל בע"מ | B8: 2025 | C8: 12 | D8: נמצוב אריאל חיים | E8: R&D | F8: 11 | G8: 0 | H8: 8 | I8: ש | J8: מקד' אופצ' | K8: 6944.14
A9: זיסקיילר ישראל בע"מ | B9: 2025 | C9: 12 | D9: נמצוב אריאל חיים | E9: R&D | F9: 11 | G9: 1 | H9: 9 | I9: ש | J9: החזר הוצ' | K9: -391
A10: זיסקיילר ישראל בע"מ | B10: 2025 | C10: 14 | D10: סבג דני | E10: R&D | F10: 11 | G10: 0 | H10: 8 | I10: ש | J10: מקד' אופצ' | K10: 3643.67
A11: זיסקיילר ישראל בע"מ | B11: 2025 | C11: 14 | D11: סבג דני | E11: R&D | F11: 11 | G11: 1 | H11: 9 | I11: ש | J11: החזר הוצ' | K11: -208
A12: זיסקיילר ישראל בע"מ | B12: 2025 | C12: 14 | D12: סבג דני | E12: R&D | F12: 11 | G12: 2 | H12: 13 | I12: ש | J12: מניות | K12: -77367.45
A13: זיסקיילר ישראל בע"מ | B13: 2025 | C13: 14 | D13: סבג דני | E13: R&D | F13: 11 | G13: 3 | H13: 13 | I13: ש | J13: מניות | K13: -54557.91
... A151: זיסקיילר ישראל בע"מ | B151: 2025 | C151: 137 | D151: קסטל גיא | E151: R&D | F151: 11 | G151: 0 | H151: 9 | I151: ש | J151: החזר הוצ' | K151: -53.9

Sheet SBC
A1: Employee Name | B1: Type | C1: ID | D1: Exercise Date | E1: Grant Date | F1: Net gain | G1: C.RATE | H1: NetGain ILS | I1: Marginal Tax rate | J1: Capital Gain Tax Rate | K1: Marginal Income | L1: Marginal Tax | M1: Capital Gain Income | N1: Capital Tax | O1: Advance payment for tax deduction | P1: Company | Q1: Z.ID | R1: תאריך עיזבה
A2: Aboudy, Omer Alon | B2: ESPP | C2: 206963159 | D2: 45960 | E2: 45460 | F2: 5565.8513 | G2: 3.2348 | H2: =F2*G2 -> 18004.416 | I2: 0.6217 | J2: 0.3 | K2: 18004.416 | L2: =I2*K2 -> 11193.345 | M2: 0 | N2: =M2*J2 -> 0 | O2: 11193.345 | P2: ZSCALER | Q2: Z30392 | R2: 0
A3: Aboudy, Omer Alon | B3: ESPP | C3: 206963159 | D3: 45960 | E3: 45642 | F3: 4606.2218 | G3: 3.2348 | H3: =F3*G3 -> 14900.206 | I3: 0.6217 | J3: 0.3 | K3: 14900.206 | L3: =I3*K3 -> 9263.4582 | M3: 0 | N3: =M3*J3 -> 0 | O3: 9263.4582 | P3: ZSCALER | Q3: Z30392 | R3: 0
A4: Aharon, Oded | B4: RSU | C4: 32949166 | D4: 45943 | E4: 45551 | F4: 4391.9658 | G4: 3.276 | H4: 14388.08 | I4: 0.6217 | J4: 0.3 | K4: 14388.08 | L4: =I4*K4 -> 8945.0694 | M4: 0 | N4: =M4*J4 -> 0 | O4: 8945.0694 | P4: ZSCALER | Q4: Z28055 | R4: 0
A5: Almaz, Assaf | B5: RSU | C5: 28831709 | D5: 45953 | E5: 45043 | F5: 18759.358 | G5: 3.2348 | H5: 60682.77 | I5: 0.6217 | J5: 0.3 | K5: 20911.833 | L5: =I5*K5 -> 13000.887 | M5: 39770.937 | N5: =M5*J5 -> 11931.281 | O5: 24932.168 | P5: ZSCALER | Q5: Z26533 | R5: 0
A6: Almaz, Assaf | B6: RSU | C6: 28831709 | D6: 45953 | E6: 45043 | F6: 18759.358 | G6: 3.2348 | H6: 60682.77 | I6: 0.6217 | J6: 0.3 | K6: 20911.833 | L6: =I6*K6 -> 13000.887 | M6: 39770.937 | N6: =M6*J6 -> 11931.281 | O6: 24932.168 | P6: ZSCALER | Q6: Z26533 | R6: 0
A7: Almaz, Assaf | B7: RSU | C7: 28831709 | D7: 45954 | E7: 44894 | F7: 133599.89 | G7: 3.2262 | H7: 431019.98 | I7: 0.6217 | J7: 0.3 | K7: 186804.61 | L7: =I7*K7 -> 116136.42 | M7: 244215.37 | N7: =M7*J7 -> 73264.612 | O7: 189401.04 | P7: ZSCALER | Q7: Z26533 | R7: 0
A8: Almaz, Assaf | B8: RSU | C8: 28831709 | D8: 45954 | E8: 45177 | F8: 24261.482 | G8: 3.2262 | H8: 78272.394 | I8: 0.6217 | J8: 0.3 | K8: 35666.632 | L8: =I8*K8 -> 22173.945 | M8: 42605.761 | N8: =M8*J8 -> 12781.728 | O8: 34955.674 | P8: ZSCALER | Q8: Z26533 | R8: 0
A9: Almaz, Assaf | B9: RSU | C9: 28831709 | D9: 45954 | E9: 45043 | F9: 19732.672 | G9: 3.2262 | H9: 63661.547 | I9: 0.6217 | J9: 0.3 | K9: 20852.493 | L9: =I9*K9 -> 12963.995 | M9: 42809.053 | N9: =M9*J9 -> 12842.716 | O9: 25806.711 | P9: ZSCALER | Q9: Z26533 | R9: 0
A10: Almaz, Assaf | B10: RSU | C10: 28831709 | D10: 45954 | E10: 44894 | F10: 133599.89 | G10: 3.2262 | H10: 431019.98 | I10: 0.6217 | J10: 0.3 | K10: 186804.61 | L10: =I10*K10 -> 116136.42 | M10: 244215.37 | N10: =M10*J10 -> 73264.612 | O10: 189401.04 | P10: ZSCALER | Q10: Z26533 | R10: 0
A11: Almaz, Assaf | B11: RSU | C11: 28831709 | D11: 45954 | E11: 45177 | F11: 24584.969 | G11: 3.2262 | H11: 79316.025 | I11: 0.6217 | J11: 0.3 | K11: 36142.187 | L11: =I11*K11 -> 22469.598 | M11: 43173.838 | N11: =M11*J11 -> 12952.151 | O11: 35421.749 | P11: ZSCALER | Q11: Z26533 | R11: 0
A12: Almaz, Assaf | B12: RSU | C12: 28831709 | D12: 45954 | E12: 45043 | F12: 19732.672 | G12: 3.2262 | H12: 63661.547 | I12: 0.6217 | J12: 0.3 | K12: 20852.493 | L12: =I12*K12 -> 12963.995 | M12: 42809.053 | N12: =M12*J12 -> 12842.716 | O12: 25806.711 | P12: ZSCALER | Q12: Z26533 | R12: 0
A13: Almaz, Assaf | B13: RSU | C13: 28831709 | D13: 45954 | E13: 44894 | F13: 133923.38 | G13: 3.2262 | H13: 432063.61 | I13: 0.6217 | J13: 0.3 | K13: 187256.92 | L13: =I13*K13 -> 116417.63 | M13: 244806.69 | N13: =M13*J13 -> 73442.008 | O13: 189859.63 | P13: ZSCALER | Q13: Z26533 | R13: 0
A14: Almaz, Assaf | B14: ESPP | C14: 28831709 | D14: 45954 | E14: 45275 | F14: 13874.942 | G14: 3.2262 | H14: =F14*G14 -> 44763.337 | I14: 0.6217 | J14: 0.3 | K14: 44763.337 | L14: =I14*K14 -> 27829.367 | M14: 0 | N14: =M14*J14 -> 0 | O14: 27829.367 | P14: ZSCALER | Q14: Z26533 | R14: 0
A15: Artemov, Vitaly | B15: RSU | C15: 321285512 | D15: 45957 | E15: 45177 | F15: 13975.047 | G15: 3.2292 | H15: 45128.223 | I15: 0.6217 | J15: 0.3 | K15: 20466.45 | L15: =I15*K15 -> 12723.992 | M15: 24661.773 | N15: =M15*J15 -> 7398.5318 | O15: 20122.524 | P15: ZSCALER | Q15: Z25694 | R15: 0
A16: Artemov, Vitaly | B16: RSU | C16: 321285512 | D16: 45957 | E16: 44753 | F16: 41925.142 | G16: 3.2292 | H16: 135384.67 | I16: 0.6217 | J16: 0.3 | K16: 64268.106 | L16: =I16*K16 -> 39955.482 | M16: 71116.562 | N16: =M16*J16 -> 21334.969 | O16: 61290.45 | P16: ZSCALER | Q16: Z25694 | R16: 0
A17: Artemov, Vitaly | B17: RSU | C17: 321285512 | D17: 45957 | E17: 45177 | F17: 13975.047 | G17: 3.2292 | H17: 45128.223 | I17: 0.6217 | J17: 0.3 | K17: 20466.45 | L17: =I17*K17 -> 12723.992 | M17: 24661.773 | N17: =M17*J17 -> 7398.5318 | O17: 20122.524 | P17: ZSCALER | Q17: Z25694 | R17: 0
A18: Artemov, Vitaly | B18: RSU | C18: 321285512 | D18: 45957 | E18: 45177 | F18: 13975.047 | G18: 3.2292 | H18: 45128.223 | I18: 0.6217 | J18: 0.3 | K18: 20466.45 | L18: =I18*K18 -> 12723.992 | M18: 24661.773 | N18: =M18*J18 -> 7398.5318 | O18: 20122.524 | P18: ZSCALER | Q18: Z25694 | R18: 0
A19: Artemov, Vitaly | B19: RSU | C19: 321285512 | D19: 45957 | E19: 45177 | F19: 13975.047 | G19: 3.2292 | H19: 45128.223 | I19: 0.6217 | J19: 0.3 | K19: 20466.45 | L19: =I19*K19 -> 12723.992 | M19: 24661.773 | N19: =M19*J19 -> 7398.5318 | O19: 20122.524 | P19: ZSCALER | Q19: Z25694 | R19: 0
A20: Artemov, Vitaly | B20: RSU | C20: 321285512 | D20: 45957 | E20: 45177 | F20: 14300.048 | G20: 3.2292 | H20: 46177.716 | I20: 0.6217 | J20: 0.3 | K20: 20942.414 | L20: =I20*K20 -> 13019.899 | M20: 25235.302 | N20: =M20*J20 -> 7570.5907 | O20: 20590.49 | P20: ZSCALER | Q20: Z25694 | R20: 0
A21: Artemov, Vitaly | B21: RSU | C21: 321285512 | D21: 45957 | E21: 45177 | F21: 13975.047 | G21: 3.2292 | H21: 45128.223 | I21: 0.6217 | J21: 0.3 | K21: 20466.45 | L21: =I21*K21 -> 12723.992 | M21: 24661.773 | N21: =M21*J21 -> 7398.5318 | O21: 20122.524 | P21: ZSCALER | Q21: Z25694 | R21: 0
A22: Artemov, Vitaly | B22: RSU | C22: 321285512 | D22: 45957 | E22: 45177 | F22: 14300.048 | G22: 3.2292 | H22: 46177.716 | I22: 0.6217 | J22: 0.3 | K22: 20942.414 | L22: =I22*K22 -> 13019.899 | M22: 25235.302 | N22: =M22*J22 -> 7570.5907 | O22: 20590.49 | P22: ZSCALER | Q22: Z25694 | R22: 0
A23: Artemov, Vitaly | B23: RSU | C23: 321285512 | D23: 45957 | E23: 45177 | F23: 13975.047 | G23: 3.2292 | H23: 45128.223 | I23: 0.6217 | J23: 0.3 | K23: 20466.45 | L23: =I23*K23 -> 12723.992 | M23: 24661.773 | N23: =M23*J23 -> 7398.5318 | O23: 20122.524 | P23: ZSCALER | Q23: Z25694 | R23: 0
A24: Artemov, Vitaly | B24: RSU | C24: 321285512 | D24: 45957 | E24: 45043 | F24: 12025.041 | G24: 3.2292 | H24: 38831.261 | I24: 0.6217 | J24: 0.3 | K24: 12658.761 | L24: =I24*K24 -> 7869.9518 | M24: 26172.5 | N24: =M24*J24 -> 7851.7501 | O24: 15721.702 | P24: ZSCALER | Q24: Z25694 | R24: 0
A25: Assayag, Jonathan | B25: RSU | C25: 207763806 | D25: 45954 | E25: 45177 | F25: 7059.697 | G25: 3.2262 | H25: 22775.995 | I25: 0.6217 | J25: 0.3 | K25: 10462.488 | L25: =I25*K25 -> 6504.529 | M25: 12313.506 | N25: =M25*J25 -> 3694.0519 | O25: 10198.581 | P25: ZSCALER | Q25: Z23077 | R25: 0
A26: Assayag, Jonathan | B26: RSU | C26: 207763806 | D26: 45954 | E26: 44537 | F26: 7380.5924 | G26: 3.2262 | H26: 23811.267 | I26: 0.6217 | J26: 0.3 | K26: 23811.267 | L26: =I26*K26 -> 14803.465 | M26: 0 | N26: =M26*J26 -> 0 | O26: 14803.465 | P26: ZSCALER | Q26: Z23077 | R26: 0
... A115: Meyuhas, Eden | B115: RSU | C115: 318638038 | D115: 45957 | E115: 44630 | F115: 12686.725 | G115: 3.2292 | H115: 40967.974 | I115: 0.6217 | J115: 0.3 | K115: 31429.789 | L115: =I115*K115 -> 19539.9 | M115: 9538.1848 | N115: =M115*J115 -> 2861.4554 | O115: 22401.355 | P115: ZSCALER | Q115: Z24243 | R115: 0
A116: Oren, Sela Ari | B116: ESPP | C116: 201179025 | D116: 45939 | E116: 45824 | F116: 3269.8783 | G116: 3.276 | H116: =F116*G116 -> 10712.121 | I116: 0.6217 | J116: 0.3 | K116: 10712.121 | L116: =I116*K116 -> 6659.7258 | M116: 0 | N116: =M116*J116 -> 0 | O116: 6659.7258 | P116: ZSCALER | Q116: Z32650 | R116: 0
A117: Oren, Sela Ari | B117: ESPP | C117: 201179025 | D117: 45958 | E117: 45824 | F117: 3434.8042 | G117: 3.2348 | H117: =F117*G117 -> 11110.905 | I117: 0.6217 | J117: 0.3 | K117: 11110.905 | L117: =I117*K117 -> 6907.6494 | M117: 0 | N117: =M117*J117 -> 0 | O117: 6907.6494 | P117: ZSCALER | Q117: Z32650 | R117: 0
A118: Perah, Oleg | B118: RSU | C118: 314349622 | D118: 45932 | E118: 45177 | F118: 3360.8682 | G118: 3.2611 | H118: 10960.127 | I118: 0.6217 | J118: 0.3 | K118: 5288.4854 | L118: =I118*K118 -> 3287.8514 | M118: 5671.642 | N118: =M118*J118 -> 1701.4926 | O118: 4989.344 | P118: ZSCALER | Q118: Z25730 | R118: 0
A119: Perah, Oleg | B119: RSU | C119: 314349622 | D119: 45932 | E119: 44753 | F119: 19859.676 | G119: 3.2611 | H119: 64764.389 | I119: 0.6217 | J119: 0.3 | K119: 32709.917 | L119: =I119*K119 -> 20335.756 | M119: 32054.472 | N119: =M119*J119 -> 9616.3415 | O119: 29952.097 | P119: ZSCALER | Q119: Z25730 | R119: 0
A120: Perah, Oleg | B120: RSU | C120: 314349622 | D120: 45932 | E120: 44753 | F120: 19859.676 | G120: 3.2611 | H120: 64764.389 | I120: 0.6217 | J120: 0.3 | K120: 32709.917 | L120: =I120*K120 -> 20335.756 | M120: 32054.472 | N120: =M120*J120 -> 9616.3415 | O120: 29952.097 | P120: ZSCALER | Q120: Z25730 | R120: 0
A121: Perah, Oleg | B121: RSU | C121: 314349622 | D121: 45932 | E121: 45177 | F121: 3666.4017 | G121: 3.2611 | H121: 11956.503 | I121: 0.6217 | J121: 0.3 | K121: 5769.2568 | L121: =I121*K121 -> 3586.7469 | M121: 6187.2458 | N121: =M121*J121 -> 1856.1738 | O121: 5442.9207 | P121: ZSCALER | Q121: Z25730 | R121: 0
A122: Perah, Oleg | B122: RSU | C122: 314349622 | D122: 45932 | E122: 45177 | F122: 3666.4017 | G122: 3.2611 | H122: 11956.503 | I122: 0.6217 | J122: 0.3 | K122: 5769.2568 | L122: =I122*K122 -> 3586.7469 | M122: 6187.2458 | N122: =M122*J122 -> 1856.1738 | O122: 5442.9207 | P122: ZSCALER | Q122: Z25730 | R122: 0
A123: Perah, Oleg | B123: RSU | C123: 314349622 | D123: 45932 | E123: 45177 | F123: 3666.4017 | G123: 3.2611 | H123: 11956.503 | I123: 0.6217 | J123: 0.3 | K123: 5769.2568 | L123: =I123*K123 -> 3586.7469 | M123: 6187.2458 | N123: =M123*J123 -> 1856.1738 | O123: 5442.9207 | P123: ZSCALER | Q123: Z25730 | R123: 0
A124: Perah, Oleg | B124: RSU | C124: 314349622 | D124: 45932 | E124: 44753 | F124: 19859.676 | G124: 3.2611 | H124: 64764.389 | I124: 0.6217 | J124: 0.3 | K124: 32709.917 | L124: =I124*K124 -> 20335.756 | M124: 32054.472 | N124: =M124*J124 -> 9616.3415 | O124: 29952.097 | P124: ZSCALER | Q124: Z25730 | R124: 0
A125: Perah, Oleg | B125: RSU | C125: 314349622 | D125: 45932 | E125: 44753 | F125: 19859.676 | G125: 3.2611 | H125: 64764.389 | I125: 0.6217 | J125: 0.3 | K125: 32709.917 | L125: =I125*K125 -> 20335.756 | M125: 32054.472 | N125: =M125*J125 -> 9616.3415 | O125: 29952.097 | P125: ZSCALER | Q125: Z25730 | R125: 0
A126: Perah, Oleg | B126: RSU | C126: 314349622 | D126: 45932 | E126: 44753 | F126: 19859.676 | G126: 3.2611 | H126: 64764.389 | I126: 0.6217 | J126: 0.3 | K126: 32709.917 | L126: =I126*K126 -> 20335.756 | M126: 32054.472 | N126: =M126*J126 -> 9616.3415 | O126: 29952.097 | P126: ZSCALER | Q126: Z25730 | R126: 0
A127: Perah, Oleg | B127: RSU | C127: 314349622 | D127: 45932 | E127: 45177 | F127: 3666.4017 | G127: 3.2611 | H127: 11956.503 | I127: 0.6217 | J127: 0.3 | K127: 5769.2568 | L127: =I127*K127 -> 3586.7469 | M127: 6187.2458 | N127: =M127*J127 -> 1856.1738 | O127: 5442.9207 | P127: ZSCALER | Q127: Z25730 | R127: 0
A128: Perah, Oleg | B128: RSU | C128: 314349622 | D128: 45932 | E128: 45043 | F128: 4583.0021 | G128: 3.2611 | H128: 14945.628 | I128: 0.6217 | J128: 0.3 | K128: 5184.2102 | L128: =I128*K128 -> 3223.0235 | M128: 9761.418 | N128: =M128*J128 -> 2928.4254 | O128: 6151.4489 | P128: ZSCALER | Q128: Z25730 | R128: 0
A129: Perah, Oleg | B129: RSU | C129: 314349622 | D129: 45932 | E129: 44753 | F129: 19859.676 | G129: 3.2611 | H129: 64764.389 | I129: 0.6217 | J129: 0.3 | K129: 32709.917 | L129: =I129*K129 -> 20335.756 | M129: 32054.472 | N129: =M129*J129 -> 9616.3415 | O129: 29952.097 | P129: ZSCALER | Q129: Z25730 | R129: 0
... A132: Perah, Oleg | B132: RSU | C132: 314349622 | D132: 45932 | E132: 45177 | F132: 3666.4017 | G132: 3.2611 | H132: 11956.503 | I132: 0.6217 | J132: 0.3 | K132: 5769.2568 | L132: =I132*K132 -> 3586.7469 | M132: 6187.2458 | N132: =M132*J132 -> 1856.1738 | O132: 5442.9207 | P132: ZSCALER | Q132: Z25730 | R132: 0
A133: Rosenblum, Alon | B133: ESPP | C133: 301380788 | D133: 45943 | E133: 45460 | F133: 12804.298 | G133: 3.276 | H133: =F133*G133 -> 41946.881 | I133: 0.6217 | J133: 0.3 | K133: 41946.881 | L133: =I133*K133 -> 26078.376 | M133: 0 | N133: =M133*J133 -> 0 | O133: 26078.376 | P133: Canonic | Q133: Z28401 | R133: 0
A134: Rozenzweig, Shmuel | B134: ESPP | C134: 11629599 | D134: 45940 | E134: 45824 | F134: 10284.845 | G134: 3.276 | H134: =F134*G134 -> 33693.152 | I134: 0.6217 | J134: 0.3 | K134: 33693.152 | L134: =I134*K134 -> 20947.033 | M134: 0 | N134: =M134*J134 -> 0 | O134: 20947.033 | P134: ZSCALER | Q134: Z27260 | R134: 0
A135: Rybak, Ilya | B135: RSU | C135: 304332992 | D135: 45953 | E135: 45177 | F135: 8492.0387 | G135: 3.2348 | H135: 27470.047 | I135: 0.6217 | J135: 0.3 | K135: 12874.959 | L135: =I135*K135 -> 8004.3622 | M135: 14595.088 | N135: =M135*J135 -> 4378.5263 | O135: 12382.888 | P135: ZSCALER | Q135: Z26721 | R135: 0
A136: Rybak, Ilya | B136: RSU | C136: 304332992 | D136: 45953 | E136: 45177 | F136: 8492.0387 | G136: 3.2348 | H136: 27470.047 | I136: 0.6217 | J136: 0.3 | K136: 12874.959 | L136: =I136*K136 -> 8004.3622 | M136: 14595.088 | N136: =M136*J136 -> 4378.5263 | O136: 12382.888 | P136: ZSCALER | Q136: Z26721 | R136: 0
A137: Rybak, Ilya | B137: RSU | C137: 304332992 | D137: 45953 | E137: 45177 | F137: 8492.0387 | G137: 3.2348 | H137: 27470.047 | I137: 0.6217 | J137: 0.3 | K137: 12874.959 | L137: =I137*K137 -> 8004.3622 | M137: 14595.088 | N137: =M137*J137 -> 4378.5263 | O137: 12382.888 | P137: ZSCALER | Q137: Z26721 | R137: 0
A138: Rybak, Ilya | B138: RSU | C138: 304332992 | D138: 45953 | E138: 45177 | F138: 8492.0387 | G138: 3.2348 | H138: 27470.047 | I138: 0.6217 | J138: 0.3 | K138: 12874.959 | L138: =I138*K138 -> 8004.3622 | M138: 14595.088 | N138: =M138*J138 -> 4378.5263 | O138: 12382.888 | P138: ZSCALER | Q138: Z26721 | R138: 0
A139: Rybak, Ilya | B139: RSU | C139: 304332992 | D139: 45953 | E139: 45177 | F139: 8492.0387 | G139: 3.2348 | H139: 27470.047 | I139: 0.6217 | J139: 0.3 | K139: 12874.959 | L139: =I139*K139 -> 8004.3622 | M139: 14595.088 | N139: =M139*J139 -> 4378.5263 | O139: 12382.888 | P139: ZSCALER | Q139: Z26721 | R139: 0
A140: Rybak, Ilya | B140: RSU | C140: 304332992 | D140: 45953 | E140: 45177 | F140: 8492.0387 | G140: 3.2348 | H140: 27470.047 | I140: 0.6217 | J140: 0.3 | K140: 12874.959 | L140: =I140*K140 -> 8004.3622 | M140: 14595.088 | N140: =M140*J140 -> 4378.5263 | O140: 12382.888 | P140: ZSCALER | Q140: Z26721 | R140: 0
A141: Rybak, Ilya | B141: RSU | C141: 304332992 | D141: 45961 | E141: 45043 | F141: 7249.0009 | G141: 3.2516 | H141: 23570.851 | I141: 0.6217 | J141: 0.3 | K141: 7578.9667 | L141: =I141*K141 -> 4711.8436 | M141: 15991.885 | N141: =M141*J141 -> 4797.5654 | O141: 9509.409 | P141: ZSCALER | Q141: Z26721 | R141: 0
A142: Rybak, Ilya | B142: RSU | C142: 304332992 | D142: 45961 | E142: 45177 | F142: 8896.5011 | G142: 3.2516 | H142: 28927.863 | I142: 0.6217 | J142: 0.3 | K142: 12940.078 | L142: =I142*K142 -> 8044.8463 | M142: 15987.785 | N142: =M142*J142 -> 4796.3356 | O142: 12841.182 | P142: ZSCALER | Q142: Z26721 | R142: 0
A143: Rybak, Ilya | B143: RSU | C143: 304332992 | D143: 45961 | E143: 44844 | F143: 32291.004 | G143: 3.2516 | H143: 104997.43 | I143: 0.6217 | J143: 0.3 | K143: 53065.506 | L143: =I143*K143 -> 32990.825 | M143: 51931.923 | N143: =M143*J143 -> 15579.577 | O143: 48570.402 | P143: ZSCALER | Q143: Z26721 | R143: 0
A144: Rybak, Ilya | B144: RSU | C144: 304332992 | D144: 45961 | E144: 45177 | F144: 8896.5011 | G144: 3.2516 | H144: 28927.863 | I144: 0.6217 | J144: 0.3 | K144: 12940.078 | L144: =I144*K144 -> 8044.8463 | M144: 15987.785 | N144: =M144*J144 -> 4796.3356 | O144: 12841.182 | P144: ZSCALER | Q144: Z26721 | R144: 0
A145: Sabag, Daniel | B145: RSU | C145: 38075941 | D145: 45936 | E145: 45043 | F145: 8666.6783 | G145: 3.2722 | H145: 28359.105 | I145: 0.6217 | J145: 0.3 | K145: 9709.2836 | L145: =I145*K145 -> 6036.2616 | M145: 18649.821 | N145: =M145*J145 -> 5594.9463 | O145: 11631.208 | P145: ZSCALER | Q145: Z22260 | R145: 0
A146: Sabag, Daniel | B146: RSU | C146: 38075941 | D146: 45936 | E146: 45043 | F146: 8357.1541 | G146: 3.2722 | H146: 27346.279 | I146: 0.6217 | J146: 0.3 | K146: 9362.5235 | L146: =I146*K146 -> 5820.6808 | M146: 17983.756 | N146: =M146*J146 -> 5395.1268 | O146: 11215.808 | P146: ZSCALER | Q146: Z22260 | R146: 0
... A188: Zukerman, Bar | B188: RSU | C188: 34890491 | D188: 45958 | E188: 45043 | F188: 4898.6706 | G188: 3.2348 | H188: 15846.22 | I188: 0.6217 | J188: 0.3 | K188: 5139.1288 | L188: =I188*K188 -> 3194.9964 | M188: 10707.091 | N188: =M188*J188 -> 3212.1273 | O188: 6407.1237 | P188: ZSCALER | Q188: Z26200 | R188: 0
A189: Zukerman, Bar | B189: ESPP | C189: 34890491 | D189: 45958 | E189: 45092 | F189: 17246.287 | G189: 3.2348 | H189: =F189*G189 -> 55788.289 | I189: 0.6217 | J189: 0.3 | K189: 14311.027 | L189: =I189*K189 -> 8897.1652 | M189: 41477.263 | N189: =M189*J189 -> 12443.179 | O189: 21340.344 | P189: ZSCALER | Q189: Z26200 | R189: 0
O192: =SUM(O2:O189) -> 5075884.5 | P192: סה"כ דוח שכר
O194: 22 | P194: עמלת העברה
O196: =O192-O194 -> 5075862.5 | P196: סכום סופי להעברה

Sheet Link
A1: בס"ד
C2: עמודת קוד עובד | D2: =Client!A1 -> No. | F2: קוד עובד במערכת | G2: =System!C1 -> מספר עובד | I2: קוד עובד | J2: מספר עובד | N2: מס תז בקובץ SBC | O2: ID
C3: שם במערכת | D3: =Client!D1 -> Employee's name | F3: קוד רכיב במערכת | G3: =System!F1 -> מספר רכיב | I3: עמודת קוד | J3: מספר ניכוי | N3: מס תז בקובץ הלקוח | O3: ID
C4: הפרש זניח בסכומים | D4: 0.0055 | F4: שם רכיב במערכת | G4: =System!G1 -> שם רכיב שכר | I4: עמודת שם ניכוי | J4: שם הניכוי | N4: סוג המרכיב | O4: Type
F5: סכום במערכת | G5: =System!H1 -> סיכום ברוטו | I5: עמודת סכום | J5: סכום הניכוי
C7: רשימת קודים בקובץ לקוח | F7: רשימת קודי שכר לא לבדיקה | I7: התאמת ניכויים - רשימת קודים בקובץ לקוח | M7: התאמת רכיבי SBC לרכיבי שכר וניכויים
C8: ItemName | D8: Code | F8: Code | G8: ItemName | I8: ItemName | J8: Code | K8: Sign | M8: InsType | N8: Col | O8: Deductions | P8: System
C9: Salary | D9: 1 | F9: 25 | G9: =VLOOKUP(F9,System!F:G,2,0) -> פיצוי שווי | I9: ESPP Contribution - Amount | J9: 8 | K9: 1 | M9: RSU | N9: Marginal Income | P9: 15
C10: Global overtime | D10: 6 | F10: 91 | G10: =VLOOKUP(F10,System!F:G,2,0) -> זק.השתלמות | I10: Reimbursement | J10: 9 | K10: -1 | M10: RSU | N10: Marginal Tax | O10: 13
C11: BIK - Mobile Reimbursment - to be grossed up | D11: 3 | F11: 93 | G11: =VLOOKUP(F11,System!F:G,2,0) -> זק.תגמולים | M11: RSU | N11: Capital Gain Income | P11: 62
C12: Travel Allowance | D12: 4 | F12: 15 | G12: =VLOOKUP(F12,System!F:G,2,0) -> שווי מניות פירותי | M12: RSU | N12: Capital Tax | O12: 13
F13: 62 | G13: =VLOOKUP(F13,System!F:G,2,0) -> שווי מניות הוני 25%
C14: Phone value | D14: 5 | G14: =VLOOKUP(F14,System!F:G,2,0) -> #N/A | M14: ESPP | N14: Marginal Income | P14: 61
C15: BIK- Birthday Gift (to be grossed up) | D15: 22 | G15: =VLOOKUP(F15,System!F:G,2,0) -> #N/A | M15: ESPP | N15: Marginal Tax | O15: 16
C16: Referral Bonus | D16: 9 | G16: =VLOOKUP(F16,System!F:G,2,0) -> #N/A | M16: ESPP | N16: Capital Gain Income | P16: 75
C17: BIK Health Insurance (to be grossed up) | D17: 51 | G17: =VLOOKUP(F17,System!F:G,2,0) -> #N/A | M17: ESPP | N17: Capital Tax | O17: 16
C18: BIK - Mobile Reimbursment - to be grossed up | D18: 24 | G18: =VLOOKUP(F18,System!F:G,2,0) -> #N/A
C19: BIK - Meals - October 2025 (EE bears the tax) | D19: 24 | G19: =VLOOKUP(F19,System!F:G,2,0) -> #N/A
C20: BIK Lunch Meals- (to be grossed up) October 2025 | D20: 24 | G20: =VLOOKUP(F20,System!F:G,2,0) -> #N/A
C21: BIK Dinner Meals- (to be grossed up) October 2025 | D21: 24 | G21: =VLOOKUP(F21,System!F:G,2,0) -> #N/A
G22: =VLOOKUP(F22,System!F:G,2,0) -> #N/A
G23: =VLOOKUP(F23,System!F:G,2,0) -> #N/A
G24: =VLOOKUP(F24,System!F:G,2,0) -> #N/A

Sheet Payroll_Findings
A1: {=_xlfn._xlws.PY(0,0,EmpID,EmpName,SysEmpID,SysCode,SysItemName,SysValue,MinDiff,ClientData,SystemData,Codes,IgnoreCodes)} -> No. | B1: Employee's name | C1: Code | D1: value | E1: מספר עובד | F1: מספר רכיב | G1: שם רכיב שכר | H1: סיכום ברוטו
A2: 4 | B2: Leonid Geldin | C2: 3 | D2: 115 | E2: 4 | F2: 3 | G2: טלפון | H2: 230
A3: 4 | B3: Leonid Geldin | C3: 24 | D3: 1115 | E3: 4 | F3: 24 | G3: שווי ארוחות | H3: 1000
A4: 6 | B4: Nadav Pozmantir | C4: 3 | D4: 115 | E4: 6 | F4: 3 | G4: טלפון | H4: 230
A5: 6 | B5: Nadav Pozmantir | C5: 24 | D5: 1115 | E5: 6 | F5: 24 | G5: שווי ארוחות | H5: 1000
A6: 8 | B6: Ido Katz | C6: 3 | D6: 115 | E6: 8 | F6: 3 | G6: טלפון | H6: 230
A7: 8 | B7: Ido Katz | C7: 24 | D7: 1115 | E7: 8 | F7: 24 | G7: שווי ארוחות | H7: 1000
A8: 11 | B8: Elad Kolberg | C8: 3 | D8: 115 | E8: 11 | F8: 3 | G8: טלפון | H8: 230
A9: 11 | B9: Elad Kolberg | C9: 24 | D9: 1115 | E9: 11 | F9: 24 | G9: שווי ארוחות | H9: 1000
A10: 12 | B10: Ariel Nemtzov | C10: 3 | D10: 115 | E10: 12 | F10: 3 | G10: טלפון | H10: 281.12
A11: 12 | B11: Ariel Nemtzov | C11: 24 | D11: 1115 | E11: 12 | F11: 24 | G11: שווי ארוחות | H11: 1000
A12: 14 | B12: Danny Sabag | C12: 3 | D12: 115 | E12: 14 | F12: 3 | G12: טלפון | H12: 304.03
A13: 14 | B13: Danny Sabag | C13: 24 | D13: 1114.96 | E13: 14 | F13: 24 | G13: שווי ארוחות | H13: 999.96
... A15: 15 | B15: Oz Molaim | C15: 4 | D15: 315 | E15: 15 | F15: 4 | G15: נסיעות | H15: 452
A16: 0 | B16: 0 | C16: 0 | D16: 0 | E16: 15 | F16: 14 | G16: תשלום הפרש מילואים | H16: 4957.79
A17: 15 | B17: Oz Molaim | C17: 24 | D17: 1055.5 | E17: 15 | F17: 24 | G17: שווי ארוחות | H17: 940.5
A18: 16 | B18: Maya Zax | C18: 3 | D18: 115 | E18: 16 | F18: 3 | G18: טלפון | H18: 218.47
A19: 16 | B19: Maya Zax | C19: 24 | D19: 815 | E19: 16 | F19: 24 | G19: שווי ארוחות | H19: 700
A20: 17 | B20: Adi Adrai | C20: 3 | D20: 115 | E20: 17 | F20: 3 | G20: טלפון | H20: 230
A21: 17 | B21: Adi Adrai | C21: 24 | D21: 853 | E21: 17 | F21: 24 | G21: שווי ארוחות | H21: 738
A22: 21 | B22: Esther Shteinberg | C22: 3 | D22: 115 | E22: 21 | F22: 3 | G22: טלפון | H22: 303.97
A23: 21 | B23: Esther Shteinberg | C23: 24 | D23: 1115 | E23: 21 | F23: 24 | G23: שווי ארוחות | H23: 1000
A24: 22 | B24: Adam Hudeda | C24: 3 | D24: 115 | E24: 22 | F24: 3 | G24: טלפון | H24: 303.98
A25: 22 | B25: Adam Hudeda | C25: 4 | D25: 315 | E25: 22 | F25: 4 | G25: נסיעות | H25: 452
A26: 22 | B26: Adam Hudeda | C26: 24 | D26: 1115 | E26: 22 | F26: 24 | G26: שווי ארוחות | H26: 1000
A27: 23 | B27: Ofer Yarom | C27: 3 | D27: 115 | E27: 23 | F27: 3 | G27: טלפון | H27: 230
A28: 23 | B28: Ofer Yarom | C28: 24 | D28: 1110.72 | E28: 23 | F28: 24 | G28: שווי ארוחות | H28: 995.72
... A31: 26 | B31: Dani Rubin | C31: 3 | D31: 115 | E31: 26 | F31: 3 | G31: טלפון | H31: 304
A32: 0 | B32: 0 | C32: 0 | D32: 0 | E32: 26 | F32: 14 | G32: תשלום הפרש מילואים | H32: 2308
A33: 26 | B33: Dani Rubin | C33: 24 | D33: 1115 | E33: 26 | F33: 24 | G33: שווי ארוחות | H33: 1000
A34: 27 | B34: Jonathan Assayag | C34: 3 | D34: 115 | E34: 27 | F34: 3 | G34: טלפון | H34: 303.97
A35: 0 | B35: 0 | C35: 0 | D35: 0 | E35: 27 | F35: 14 | G35: תשלום הפרש מילואים | H35: 1690
A36: 27 | B36: Jonathan Assayag | C36: 24 | D36: 1115 | E36: 27 | F36: 24 | G36: שווי ארוחות | H36: 1000
A37: 28 | B37: Tamir Leshetz | C37: 3 | D37: 115 | E37: 28 | F37: 3 | G37: טלפון | H37: 283.01
A38: 28 | B38: Tamir Leshetz | C38: 24 | D38: 1115 | E38: 28 | F38: 24 | G38: שווי ארוחות | H38: 1000
A39: 30 | B39: Gal Shvinkelstein | C39: 3 | D39: 115 | E39: 30 | F39: 3 | G39: טלפון | H39: 304
A40: 30 | B40: Gal Shvinkelstein | C40: 24 | D40: 1115 | E40: 30 | F40: 24 | G40: שווי ארוחות | H40: 1000
A41: 32 | B41: Gal Sosin | C41: 3 | D41: 115 | E41: 32 | F41: 3 | G41: טלפון | H41: 230
A42: 32 | B42: Gal Sosin | C42: 24 | D42: 1115 | E42: 32 | F42: 24 | G42: שווי ארוחות | H42: 1000
A43: 35 | B43: Keren Zilberman | C43: 3 | D43: 115 | E43: 35 | F43: 3 | G43: טלפון | H43: 218.45
A44: 35 | B44: Keren Zilberman | C44: 24 | D44: 1115 | E44: 35 | F44: 24 | G44: שווי ארוחות | H44: 1000
A45: 36 | B45: Amit Bar | C45: 3 | D45: 115 | E45: 36 | F45: 3 | G45: טלפון | H45: 216.93
A46: 36 | B46: Amit Bar | C46: 4 | D46: 315 | E46: 36 | F46: 4 | G46: נסיעות | H46: 474.6
A47: 36 | B47: Amit Bar | C47: 24 | D47: 1283 | E47: 36 | F47: 24 | G47: שווי ארוחות | H47: 1168
... A50: 41 | B50: Shoham Shimon Danino | C50: 3 | D50: 115 | E50: 41 | F50: 3 | G50: טלפון | H50: 229.99
A51: 0 | B51: 0 | C51: 0 | D51: 0 | E51: 41 | F51: 14 | G51: תשלום הפרש מילואים | H51: 28727
A52: 41 | B52: Shoham Shimon Danino | C52: 24 | D52: 1115 | E52: 41 | F52: 24 | G52: שווי ארוחות | H52: 1000
A53: 42 | B53: Roi Inbar | C53: 3 | D53: 115 | E53: 42 | F53: 3 | G53: טלפון | H53: 303.99
A54: 42 | B54: Roi Inbar | C54: 24 | D54: 1115 | E54: 42 | F54: 24 | G54: שווי ארוחות | H54: 1000
A55: 43 | B55: Samir Dabit | C55: 3 | D55: 115 | E55: 43 | F55: 3 | G55: טלפון | H55: 283.02
A56: 43 | B56: Samir Dabit | C56: 24 | D56: 1115 | E56: 43 | F56: 24 | G56: שווי ארוחות | H56: 1000
A57: 45 | B57: Noam Yadar | C57: 3 | D57: 115 | E57: 45 | F57: 3 | G57: טלפון | H57: 303.98
A58: 45 | B58: Noam Yadar | C58: 24 | D58: 1115 | E58: 45 | F58: 24 | G58: שווי ארוחות | H58: 1000
A59: 47 | B59: Eden Meyuhas | C59: 3 | D59: 115 | E59: 47 | F59: 3 | G59: טלפון | H59: 304.05
A60: 0 | B60: 0 | C60: 0 | D60: 0 | E60: 47 | F60: 14 | G60: תשלום הפרש מילואים | H60: 25349
A61: 47 | B61: Eden Meyuhas | C61: 24 | D61: 1115 | E61: 47 | F61: 24 | G61: שווי ארוחות | H61: 1000
A62: 53 | B62: Dor Pizem | C62: 3 | D62: 115 | E62: 53 | F62: 3 | G62: טלפון | H62: 303.97
A63: 53 | B63: Dor Pizem | C63: 24 | D63: 1114.71 | E63: 53 | F63: 24 | G63: שווי ארוחות | H63: 999.71
A64: 54 | B64: Vitaly Artemov | C64: 3 | D64: 115 | E64: 54 | F64: 3 | G64: טלפון | H64: 230
A65: 54 | B65: Vitaly Artemov | C65: 24 | D65: 1115 | E65: 54 | F65: 24 | G65: שווי ארוחות | H65: 1000
A66: 55 | B66: Oleg Perah | C66: 3 | D66: 115 | E66: 55 | F66: 3 | G66: טלפון | H66: 304.02
A67: 55 | B67: Oleg Perah | C67: 24 | D67: 1115 | E67: 55 | F67: 24 | G67: שווי ארוחות | H67: 1000
A68: 56 | B68: Marat Khousid | C68: 3 | D68: 115 | E68: 56 | F68: 3 | G68: טלפון | H68: 230
A69: 56 | B69: Marat Khousid | C69: 24 | D69: 1115 | E69: 56 | F69: 24 | G69: שווי ארוחות | H69: 1000
A70: 57 | B70: Ricky Levi | C70: 3 | D70: 115 | E70: 57 | F70: 3 | G70: טלפון | H70: 304.02
A71: 57 | B71: Ricky Levi | C71: 24 | D71: 1115 | E71: 57 | F71: 24 | G71: שווי ארוחות | H71: 1000
A72: 59 | B72: Elad Goren | C72: 3 | D72: 115 | E72: 59 | F72: 3 | G72: טלפון | H72: 230
... A85: 68 | B85: Bar Zukerman | C85: 24 | D85: 1115 | E85: 68 | F85: 24 | G85: שווי ארוחות | H85: 1000
A86: 0 | B86: 0 | C86: 0 | D86: 0 | E86: 68 | F86: 61 | G86: שווי אופציות (פ) | H86: 14311.03
A87: 0 | B87: 0 | C87: 0 | D87: 0 | E87: 68 | F87: 75 | G87: שווי אופציות הוני 25 | H87: 41477.26
A88: 69 | B88: Alexander Jouravski | C88: 3 | D88: 115 | E88: 69 | F88: 3 | G88: טלפון | H88: 230
A89: 69 | B89: Alexander Jouravski | C89: 24 | D89: 1115 | E89: 69 | F89: 24 | G89: שווי ארוחות | H89: 1000
A90: 70 | B90: Sagie Vachman | C90: 3 | D90: 115 | E90: 70 | F90: 3 | G90: טלפון | H90: 230
A91: 70 | B91: Sagie Vachman | C91: 24 | D91: 945.78 | E91: 70 | F91: 24 | G91: שווי ארוחות | H91: 830.78
A92: 71 | B92: Roee Gozlan | C92: 3 | D92: 115 | E92: 71 | F92: 3 | G92: טלפון | H92: 218.45
A93: 71 | B93: Roee Gozlan | C93: 24 | D93: 120 | E93: 71 | F93: 24 | G93: שווי ארוחות | H93: 5
A94: 72 | B94: Assaf Almaz | C94: 3 | D94: 115 | E94: 72 | F94: 3 | G94: טלפון | H94: 230
A95: 72 | B95: Assaf Almaz | C95: 24 | D95: 115 | E95: 0 | F95: 0 | G95: 0 | H95: 0
A96: 0 | B96: 0 | C96: 0 | D96: 0 | E96: 72 | F96: 61 | G96: שווי אופציות (פ) | H96: 44763.34
A97: 73 | B97: Assaf Nir | C97: 3 | D97: 115 | E97: 73 | F97: 3 | G97: טלפון | H97: 230
A98: 73 | B98: Assaf Nir | C98: 24 | D98: 1115 | E98: 73 | F98: 24 | G98: שווי ארוחות | H98: 1000
A99: 74 | B99: Reuven Abramov | C99: 3 | D99: 115 | E99: 74 | F99: 3 | G99: טלפון | H99: 281.1
A100: 74 | B100: Reuven Abramov | C100: 24 | D100: 1114.27 | E100: 74 | F100: 24 | G100: שווי ארוחות | H100: 999.27
A101: 76 | B101: Roi Zentner | C101: 3 | D101: 115 | E101: 76 | F101: 3 | G101: טלפון | H101: 304.01
A102: 76 | B102: Roi Zentner | C102: 4 | D102: 315 | E102: 76 | F102: 4 | G102: נסיעות | H102: 410
A103: 76 | B103: Roi Zentner | C103: 24 | D103: 1100.3 | E103: 76 | F103: 24 | G103: שווי ארוחות | H103: 985.3
A104: 77 | B104: Shahar Inbar | C104: 3 | D104: 115 | E104: 77 | F104: 3 | G104: טלפון | H104: 230
A105: 77 | B105: Shahar Inbar | C105: 24 | D105: 1112 | E105: 77 | F105: 24 | G105: שווי ארוחות | H105: 997
A106: 78 | B106: Nir Barel | C106: 3 | D106: 115 | E106: 78 | F106: 3 | G106: טלפון | H106: 281.12
A107: 78 | B107: Nir Barel | C107: 24 | D107: 1115 | E107: 78 | F107: 24 | G107: שווי ארוחות | H107: 1000
A108: 80 | B108: Ilya Rybak | C108: 3 | D108: 115 | E108: 80 | F108: 3 | G108: טלפון | H108: 230
... A117: 84 | B117: Shmulik Rozenzweig | C117: 24 | D117: 1113.85 | E117: 84 | F117: 24 | G117: שווי ארוחות | H117: 998.85
A118: 0 | B118: 0 | C118: 0 | D118: 0 | E118: 84 | F118: 61 | G118: שווי אופציות (פ) | H118: 33693.15
A119: 85 | B119: Assaf Cohen | C119: 3 | D119: 115 | E119: 85 | F119: 3 | G119: טלפון | H119: 230
A120: 85 | B120: Assaf Cohen | C120: 24 | D120: 1115 | E120: 85 | F120: 24 | G120: שווי ארוחות | H120: 1000
A121: 86 | B121: Matanel Elhayani | C121: 3 | D121: 115 | E121: 86 | F121: 3 | G121: טלפון | H121: 230
A122: 86 | B122: Matanel Elhayani | C122: 24 | D122: 1115 | E122: 86 | F122: 24 | G122: שווי ארוחות | H122: 1000
A123: 87 | B123: Chen Dahan | C123: 3 | D123: 115 | E123: 87 | F123: 3 | G123: טלפון | H123: 281.13
A124: 87 | B124: Chen Dahan | C124: 24 | D124: 1114.1 | E124: 87 | F124: 24 | G124: שווי ארוחות | H124: 999.1
A125: 88 | B125: Amir Hazbani | C125: 3 | D125: 115 | E125: 88 | F125: 3 | G125: טלפון | H125: 281.13
...

Sheet WHT_Findings
A1: {=_xlfn._xlws.PY(1,0,DeductionCodes,DeductionData,DedEmp,DedCode,DedName,DedValue)} -> No. | B1: Employee's name | C1: ItemName | D1: value | E1: Code | F1: Sign | G1: מספר עובד | H1: מספר ניכוי | I1: שם הניכוי | J1: סכום הניכוי | K1: SignedValue

Sheet SBC_Findings
A1: {=_xlfn._xlws.PY(2,0,SBCID,ClientID,SBCType,SBCdata,SBCcodes)} -> No. | B1: Employee's name | C1: System | D1: value | E1: מספר עובד | F1: מספר רכיב | G1: שם רכיב שכר | H1: סיכום ברוטו | L1: {=_xlfn._xlws.PY(3,0)} | M1: No. | N1: Employee's name | O1: Deductions | P1: value | Q1: מספר עובד | R1: מספר ניכוי | S1: שם הניכוי | T1: סכום הניכוי
L2: 2 | M2: 14 | N2: Danny Sabag | O2: 13 | P2: 131925.35 | Q2: 14 | R2: 13 | S2: מניות | T2: -131925.36
L3: 4 | M3: 21 | N3: Esther Shteinberg | O3: 13 | P3: 74739.424 | Q3: 21 | R3: 13 | S3: מניות | T3: -74739.43
L4: 10 | M4: 28 | N4: Tamir Leshetz | O4: 13 | P4: 41745.926 | Q4: 28 | R4: 13 | S4: מניות | T4: -41745.92
L5: 29 | M5: 68 | N5: Bar Zukerman | O5: 16 | P5: 21340.344 | Q5: 68 | R5: 16 | S5: אופציות | T5: -21340.35
L6: 38 | M6: 80 | N6: Ilya Rybak | O6: 13 | P6: 158059.51 | Q6: 80 | R6: 13 | S6: מניות | T6: -158059.5

Sheet Test
A1: {=_xlfn._xlws.PY(3,0)} | B1: No. | C1: Employee's name | D1: Deductions | E1: value | F1: מספר עובד | G1: מספר ניכוי | H1: שם הניכוי | I1: סכום הניכוי
A2: 2 | B2: 14 | C2: Danny Sabag | D2: 13 | E2: 131925.35 | F2: 14 | G2: 13 | H2: מניות | I2: -131925.36
A3: 4 | B3: 21 | C3: Esther Shteinberg | D3: 13 | E3: 74739.424 | F3: 21 | G3: 13 | H3: מניות | I3: -74739.43
A4: 10 | B4: 28 | C4: Tamir Leshetz | D4: 13 | E4: 41745.926 | F4: 28 | G4: 13 | H4: מניות | I4: -41745.92
A5: 29 | B5: 68 | C5: Bar Zukerman | D5: 16 | E5: 21340.344 | F5: 68 | G5: 16 | H5: אופציות | I5: -21340.35
A6: 38 | B6: 80 | C6: Ilya Rybak | D6: 13 | E6: 158059.51 | F6: 80 | G6: 13 | H6: מניות | I6: -158059.5
